{
  "version": "https://jsonfeed.org/version/1",
  "title": "Thời sự - VnExpress RSS",
  "home_page_url": "https://vnexpress.net/rss/thoi-su.rss",
  "description": "VnExpress RSS",
  "items": [
    {
      "guid": "https://vnexpress.net/duong-sat-thiet-hai-hon-50-ty-dong-do-sat-lo-ham-bai-gio-4743567.html",
      "url": "https://vnexpress.net/duong-sat-thiet-hai-hon-50-ty-dong-do-sat-lo-ham-bai-gio-4743567.html",
      "title": "Đường sắt thiệt hại hơn 50 tỷ đồng do sạt lở hầm Bãi Gió",
      "content_html": "<a href=\"https://vnexpress.net/duong-sat-thiet-hai-hon-50-ty-dong-do-sat-lo-ham-bai-gio-4743567.html\"><img src=\"https://vcdn1-vnexpress.vnecdn.net/2024/05/08/dsc06519-1713010785-1713018468-8962-6576-1715155139.jpg?w=1200&h=0&q=100&dpr=1&fit=crop&s=xKN_nquNC75tDYhhX4fUhQ\"></a></br>Trong 10 ngày xảy ra sạt lở hầm Bãi Gió, Tổng công ty Đường sắt Việt Nam (VNR) bị thiệt hại 50,4 tỷ đồng để khắc phục sự cố, chuyển tải hành khách bằng đường bộ.",
      "summary": "<a href=\"https://vnexpress.net/duong-sat-thiet-hai-hon-50-ty-dong-do-sat-lo-ham-bai-gio-4743567.html\"><img src=\"https://vcdn1-vnexpress.vnecdn.net/2024/05/08/dsc06519-1713010785-1713018468-8962-6576-1715155139.jpg?w=1200&h=0&q=100&dpr=1&fit=crop&s=xKN_nquNC75tDYhhX4fUhQ\"></a></br>Trong 10 ngày xảy ra sạt lở hầm Bãi Gió, Tổng công ty Đường sắt Việt Nam (VNR) bị thiệt hại 50,4 tỷ đồng để khắc phục sự cố, chuyển tải hành khách bằng đường bộ.",
      "date_published": "2024-05-08T08:26:14.000Z"
    },
    {
      "guid": "https://vnexpress.net/ban-duc-noi-tren-cuu-dinh-duoc-cong-nhan-di-san-tu-lieu-the-gioi-4743548.html",
      "url": "https://vnexpress.net/ban-duc-noi-tren-cuu-dinh-duoc-cong-nhan-di-san-tu-lieu-the-gioi-4743548.html",
      "title": "Bản đúc nổi trên Cửu đỉnh được công nhận di sản tư liệu thế giới",
      "content_html": "<a href=\"https://vnexpress.net/ban-duc-noi-tren-cuu-dinh-duoc-cong-nhan-di-san-tu-lieu-the-gioi-4743548.html\"><img src=\"https://vcdn1-vnexpress.vnecdn.net/2024/05/08/cd23-2594-1715151653.jpg?w=1200&h=0&q=100&dpr=1&fit=crop&s=XRPP2OOZS5n-ihxF49cvTA\"></a></br>Những bản đúc nổi trên bảo vật quốc gia Cửu đỉnh ở Thế Tổ Miếu được UNESCO công nhận di sản tư liệu thế giới, ngày 8/5.",
      "summary": "<a href=\"https://vnexpress.net/ban-duc-noi-tren-cuu-dinh-duoc-cong-nhan-di-san-tu-lieu-the-gioi-4743548.html\"><img src=\"https://vcdn1-vnexpress.vnecdn.net/2024/05/08/cd23-2594-1715151653.jpg?w=1200&h=0&q=100&dpr=1&fit=crop&s=XRPP2OOZS5n-ihxF49cvTA\"></a></br>Những bản đúc nổi trên bảo vật quốc gia Cửu đỉnh ở Thế Tổ Miếu được UNESCO công nhận di sản tư liệu thế giới, ngày 8/5.",
      "date_published": "2024-05-08T07:40:20.000Z"
    },
    {
      "guid": "https://vnexpress.net/can-hon-174-000-ty-dong-xay-nut-giao-duong-noi-cao-toc-4743406.html",
      "url": "https://vnexpress.net/can-hon-174-000-ty-dong-xay-nut-giao-duong-noi-cao-toc-4743406.html",
      "title": "Cần hơn 174.000 tỷ đồng xây nút giao, đường nối cao tốc",
      "content_html": "<a href=\"https://vnexpress.net/can-hon-174-000-ty-dong-xay-nut-giao-duong-noi-cao-toc-4743406.html\"><img src=\"https://vcdn1-vnexpress.vnecdn.net/2024/05/08/16-dji-0539-jpg-1715141451-6083-1715141811.jpg?w=1200&h=0&q=100&dpr=1&fit=crop&s=3hVkRzuCx_YIHFXO0XTsMA\"></a></br>Các địa phương đề xuất đầu tư xây dựng nút giao, đường kết nối với tổng vốn hơn 174.000 tỷ đồng để phát huy hiệu quả các tuyến cao tốc.",
      "summary": "<a href=\"https://vnexpress.net/can-hon-174-000-ty-dong-xay-nut-giao-duong-noi-cao-toc-4743406.html\"><img src=\"https://vcdn1-vnexpress.vnecdn.net/2024/05/08/16-dji-0539-jpg-1715141451-6083-1715141811.jpg?w=1200&h=0&q=100&dpr=1&fit=crop&s=3hVkRzuCx_YIHFXO0XTsMA\"></a></br>Các địa phương đề xuất đầu tư xây dựng nút giao, đường kết nối với tổng vốn hơn 174.000 tỷ đồng để phát huy hiệu quả các tuyến cao tốc.",
      "date_published": "2024-05-08T07:04:44.000Z"
    },
    {
      "guid": "https://vnexpress.net/le-ruoc-muc-dong-o-da-nang-4743325.html",
      "url": "https://vnexpress.net/le-ruoc-muc-dong-o-da-nang-4743325.html",
      "title": "Lễ rước mục đồng ở Đà Nẵng",
      "content_html": "<a href=\"https://vnexpress.net/le-ruoc-muc-dong-o-da-nang-4743325.html\"><img src=\"https://vcdn1-vnexpress.vnecdn.net/2024/05/08/a5-1715127124-1715142131.jpg?w=1200&h=0&q=100&dpr=1&fit=crop&s=qknwYYgxemk9kgIBEUJOhg\"></a></br>Người dân làng cổ Phong Lệ rước mục đồng, làm lễ trước viên đá thần để cầu cho mưa thuận gió hòa, mùa màng tươi tốt, bội thu.",
      "summary": "<a href=\"https://vnexpress.net/le-ruoc-muc-dong-o-da-nang-4743325.html\"><img src=\"https://vcdn1-vnexpress.vnecdn.net/2024/05/08/a5-1715127124-1715142131.jpg?w=1200&h=0&q=100&dpr=1&fit=crop&s=qknwYYgxemk9kgIBEUJOhg\"></a></br>Người dân làng cổ Phong Lệ rước mục đồng, làm lễ trước viên đá thần để cầu cho mưa thuận gió hòa, mùa màng tươi tốt, bội thu.",
      "date_published": "2024-05-08T04:38:50.000Z"
    },
    {
      "guid": "https://vnexpress.net/40-xe-dien-du-lich-o-hoi-an-bi-thieu-rui-4743344.html",
      "url": "https://vnexpress.net/40-xe-dien-du-lich-o-hoi-an-bi-thieu-rui-4743344.html",
      "title": "40 xe điện du lịch ở Hội An bị thiêu rụi",
      "content_html": "<a href=\"https://vnexpress.net/40-xe-dien-du-lich-o-hoi-an-bi-thieu-rui-4743344.html\"><img src=\"https://vcdn1-vnexpress.vnecdn.net/2024/05/08/anhchay-1715132884-4849-1715132888.gif?w=1200&h=0&q=100&dpr=1&fit=crop&s=3DdUig76Bnhq5EhDiQ719Q&t=image\"></a></br>40 xe điện chở du khách tham quan Hội An bị thiêu rụi sau đám cháy ở nhà xe trường Cao đẳng Điện lực miền Trung, sáng 8/5.",
      "summary": "<a href=\"https://vnexpress.net/40-xe-dien-du-lich-o-hoi-an-bi-thieu-rui-4743344.html\"><img src=\"https://vcdn1-vnexpress.vnecdn.net/2024/05/08/anhchay-1715132884-4849-1715132888.gif?w=1200&h=0&q=100&dpr=1&fit=crop&s=3DdUig76Bnhq5EhDiQ719Q&t=image\"></a></br>40 xe điện chở du khách tham quan Hội An bị thiêu rụi sau đám cháy ở nhà xe trường Cao đẳng Điện lực miền Trung, sáng 8/5.",
      "date_published": "2024-05-08T01:35:06.000Z"
    },
    {
      "guid": "https://vnexpress.net/nuoc-ngam-o-tay-nguyen-suy-giam-khong-ngung-4743032.html",
      "url": "https://vnexpress.net/nuoc-ngam-o-tay-nguyen-suy-giam-khong-ngung-4743032.html",
      "title": "Nước ngầm ở Tây Nguyên 'suy giảm không ngừng'",
      "content_html": "<a href=\"https://vnexpress.net/nuoc-ngam-o-tay-nguyen-suy-giam-khong-ngung-4743032.html\"><img src=\"https://vcdn1-vnexpress.vnecdn.net/2024/05/07/z5317431018698-9802e091e8cc947-9420-1626-1715058202.jpg?w=1200&h=0&q=100&dpr=1&fit=crop&s=F8sR5ki83m3H2WJ3D3L7zA\"></a></br>Nhu cầu khai thác nước ngầm ở Tây Nguyên tăng cao do hạn hán và nắng nóng, khiến mực nước không ngừng hạ thấp, có nơi giảm đột biến hơn 2,3 m, theo chuyên gia.",
      "summary": "<a href=\"https://vnexpress.net/nuoc-ngam-o-tay-nguyen-suy-giam-khong-ngung-4743032.html\"><img src=\"https://vcdn1-vnexpress.vnecdn.net/2024/05/07/z5317431018698-9802e091e8cc947-9420-1626-1715058202.jpg?w=1200&h=0&q=100&dpr=1&fit=crop&s=F8sR5ki83m3H2WJ3D3L7zA\"></a></br>Nhu cầu khai thác nước ngầm ở Tây Nguyên tăng cao do hạn hán và nắng nóng, khiến mực nước không ngừng hạ thấp, có nơi giảm đột biến hơn 2,3 m, theo chuyên gia.",
      "date_published": "2024-05-07T23:00:00.000Z"
    },
    {
      "guid": "https://vnexpress.net/duong-lang-se-duoc-mo-rong-gap-doi-4743267.html",
      "url": "https://vnexpress.net/duong-lang-se-duoc-mo-rong-gap-doi-4743267.html",
      "title": "Đường Láng sẽ được mở rộng gấp đôi",
      "content_html": "<a href=\"https://vnexpress.net/duong-lang-se-duoc-mo-rong-gap-doi-4743267.html\"><img src=\"https://vcdn1-vnexpress.vnecdn.net/2024/05/08/lang1-1715094188-4719-17150956-2436-7595-1715131280.jpg?w=1200&h=0&q=100&dpr=1&fit=crop&s=4mL_TuZmKFSQSj4R_ZsAOA\"></a></br>Hà Nội sẽ mở rộng đường Láng từ khoảng 21 m cả hai chiều hiện nay lên 53,5 m, đồng thời xây dựng đường trên cao từ Ngã Tư Sở đến Cầu Giấy.",
      "summary": "<a href=\"https://vnexpress.net/duong-lang-se-duoc-mo-rong-gap-doi-4743267.html\"><img src=\"https://vcdn1-vnexpress.vnecdn.net/2024/05/08/lang1-1715094188-4719-17150956-2436-7595-1715131280.jpg?w=1200&h=0&q=100&dpr=1&fit=crop&s=4mL_TuZmKFSQSj4R_ZsAOA\"></a></br>Hà Nội sẽ mở rộng đường Láng từ khoảng 21 m cả hai chiều hiện nay lên 53,5 m, đồng thời xây dựng đường trên cao từ Ngã Tư Sở đến Cầu Giấy.",
      "date_published": "2024-05-07T22:00:00.000Z"
    },
    {
      "guid": "https://vnexpress.net/trung-bay-500-co-vat-quy-hiem-o-hai-phong-4742991.html",
      "url": "https://vnexpress.net/trung-bay-500-co-vat-quy-hiem-o-hai-phong-4742991.html",
      "title": "Trưng bày 500 cổ vật quý hiếm ở Hải Phòng",
      "content_html": "<a href=\"https://vnexpress.net/trung-bay-500-co-vat-quy-hiem-o-hai-phong-4742991.html\"><img src=\"https://vcdn1-vnexpress.vnecdn.net/2024/05/07/dsc06045-jpg-1715054385-1715066435.jpg?w=1200&h=0&q=100&dpr=1&fit=crop&s=avfOm1OoszyaftJ0TRGCdg\"></a></br>500 cổ vật quý hiếm, trong đó có 18 bảo vật quốc gia sẽ được trưng bày tại Bảo tàng Hải Phòng để người dân tham quan từ ngày 11/5 đến hết năm.",
      "summary": "<a href=\"https://vnexpress.net/trung-bay-500-co-vat-quy-hiem-o-hai-phong-4742991.html\"><img src=\"https://vcdn1-vnexpress.vnecdn.net/2024/05/07/dsc06045-jpg-1715054385-1715066435.jpg?w=1200&h=0&q=100&dpr=1&fit=crop&s=avfOm1OoszyaftJ0TRGCdg\"></a></br>500 cổ vật quý hiếm, trong đó có 18 bảo vật quốc gia sẽ được trưng bày tại Bảo tàng Hải Phòng để người dân tham quan từ ngày 11/5 đến hết năm.",
      "date_published": "2024-05-07T22:00:00.000Z"
    },
    {
      "guid": "https://vnexpress.net/tp-hcm-se-lam-tuyen-duong-mau-ve-khong-gian-do-thi-o-khu-trung-tam-4743242.html",
      "url": "https://vnexpress.net/tp-hcm-se-lam-tuyen-duong-mau-ve-khong-gian-do-thi-o-khu-trung-tam-4743242.html",
      "title": "TP HCM sẽ làm tuyến đường 'mẫu' về không gian đô thị ở khu trung tâm",
      "content_html": "<a href=\"https://vnexpress.net/tp-hcm-se-lam-tuyen-duong-mau-ve-khong-gian-do-thi-o-khu-trung-tam-4743242.html\"><img src=\"https://vcdn1-vnexpress.vnecdn.net/2024/05/07/z54180226427086b02cc4e65bc8acd-8417-1413-1715078744.jpg?w=1200&h=0&q=100&dpr=1&fit=crop&s=5I0MOSsytQZucCsL7Gj81A\"></a></br>Đường Thái Văn Lung, quận 1, dài 400 m, được đề xuất cải tạo, bổ sung các tiện ích hình thành tuyến phố kiểu mẫu về không gian đô thị, kinh phí gần 30 tỷ đồng.",
      "summary": "<a href=\"https://vnexpress.net/tp-hcm-se-lam-tuyen-duong-mau-ve-khong-gian-do-thi-o-khu-trung-tam-4743242.html\"><img src=\"https://vcdn1-vnexpress.vnecdn.net/2024/05/07/z54180226427086b02cc4e65bc8acd-8417-1413-1715078744.jpg?w=1200&h=0&q=100&dpr=1&fit=crop&s=5I0MOSsytQZucCsL7Gj81A\"></a></br>Đường Thái Văn Lung, quận 1, dài 400 m, được đề xuất cải tạo, bổ sung các tiện ích hình thành tuyến phố kiểu mẫu về không gian đô thị, kinh phí gần 30 tỷ đồng.",
      "date_published": "2024-05-07T17:00:00.000Z"
    },
    {
      "guid": "https://vnexpress.net/du-thao-quy-dinh-tach-thua-gay-kho-cho-nguoi-dan-tp-hcm-4743125.html",
      "url": "https://vnexpress.net/du-thao-quy-dinh-tach-thua-gay-kho-cho-nguoi-dan-tp-hcm-4743125.html",
      "title": "'Dự thảo quy định tách thửa gây khó cho người dân TP HCM'",
      "content_html": "<a href=\"https://vnexpress.net/du-thao-quy-dinh-tach-thua-gay-kho-cho-nguoi-dan-tp-hcm-4743125.html\"><img src=\"https://vcdn1-vnexpress.vnecdn.net/2024/05/07/z5418260741527-1d7a7eb0389b559-3179-6076-1715082563.jpg?w=1200&h=0&q=100&dpr=1&fit=crop&s=PlknZRdJtfq8hnaD-sAYnA\"></a></br>Điều kiện tách thửa đất xây dựng mới, đất hỗn hợp phải căn cứ quy hoạch chi tiết tỷ lệ 1/500 không khả thi, gây khó cho người dân thành phố, theo luật sư Nguyễn Văn Hậu.",
      "summary": "<a href=\"https://vnexpress.net/du-thao-quy-dinh-tach-thua-gay-kho-cho-nguoi-dan-tp-hcm-4743125.html\"><img src=\"https://vcdn1-vnexpress.vnecdn.net/2024/05/07/z5418260741527-1d7a7eb0389b559-3179-6076-1715082563.jpg?w=1200&h=0&q=100&dpr=1&fit=crop&s=PlknZRdJtfq8hnaD-sAYnA\"></a></br>Điều kiện tách thửa đất xây dựng mới, đất hỗn hợp phải căn cứ quy hoạch chi tiết tỷ lệ 1/500 không khả thi, gây khó cho người dân thành phố, theo luật sư Nguyễn Văn Hậu.",
      "date_published": "2024-05-07T17:00:00.000Z"
    },
    {
      "guid": "https://vnexpress.net/tim-nguoi-bo-quen-3-mieng-nghi-la-vang-khi-quyen-gop-do-cu-4743257.html",
      "url": "https://vnexpress.net/tim-nguoi-bo-quen-3-mieng-nghi-la-vang-khi-quyen-gop-do-cu-4743257.html",
      "title": "Tìm người bỏ quên 3 miếng nghi là vàng khi quyên góp đồ cũ",
      "content_html": "<a href=\"https://vnexpress.net/tim-nguoi-bo-quen-3-mieng-nghi-la-vang-khi-quyen-gop-do-cu-4743257.html\"><img src=\"https://vcdn1-vnexpress.vnecdn.net/2024/05/07/c4b07013a76806365f79-8566-1715-5477-4592-1715084548.jpg?w=1200&h=0&q=100&dpr=1&fit=crop&s=uRbVlAyDddzwvrHmWNIbnA\"></a></br>Mở túi quần áo cũ được nam thanh niên quyên góp từ thiện, nhân viên cửa hàng ở TP Thủ Đức thấy 3 miếng kim loại, 2 nhẫn nghi là vàng nên giao cho chính quyền.",
      "summary": "<a href=\"https://vnexpress.net/tim-nguoi-bo-quen-3-mieng-nghi-la-vang-khi-quyen-gop-do-cu-4743257.html\"><img src=\"https://vcdn1-vnexpress.vnecdn.net/2024/05/07/c4b07013a76806365f79-8566-1715-5477-4592-1715084548.jpg?w=1200&h=0&q=100&dpr=1&fit=crop&s=uRbVlAyDddzwvrHmWNIbnA\"></a></br>Mở túi quần áo cũ được nam thanh niên quyên góp từ thiện, nhân viên cửa hàng ở TP Thủ Đức thấy 3 miếng kim loại, 2 nhẫn nghi là vàng nên giao cho chính quyền.",
      "date_published": "2024-05-07T12:26:56.000Z"
    },
    {
      "guid": "https://vnexpress.net/duong-pho-dong-nai-tp-hcm-ngap-sau-mua-lon-4743204.html",
      "url": "https://vnexpress.net/duong-pho-dong-nai-tp-hcm-ngap-sau-mua-lon-4743204.html",
      "title": "Đường phố Đồng Nai, TP HCM ngập sau mưa lớn",
      "content_html": "<a href=\"https://vnexpress.net/duong-pho-dong-nai-tp-hcm-ngap-sau-mua-lon-4743204.html\"><img src=\"https://vcdn1-vnexpress.vnecdn.net/2024/05/07/z5418221274030-3bfb0f5d7611ebe-1425-4255-1715090819.jpg?w=1200&h=0&q=100&dpr=1&fit=crop&s=AiYyVV5BDYA5_N6ybb9WFg\"></a></br>Sau cơn mưa lớn kéo dài, nhiều đường trung tâm TP Biên Hòa và một số quận huyện TP HCM ngập 30-40 cm, người đi xe máy ngã nhào, nhà tốc mái, chiều 7/5.",
      "summary": "<a href=\"https://vnexpress.net/duong-pho-dong-nai-tp-hcm-ngap-sau-mua-lon-4743204.html\"><img src=\"https://vcdn1-vnexpress.vnecdn.net/2024/05/07/z5418221274030-3bfb0f5d7611ebe-1425-4255-1715090819.jpg?w=1200&h=0&q=100&dpr=1&fit=crop&s=AiYyVV5BDYA5_N6ybb9WFg\"></a></br>Sau cơn mưa lớn kéo dài, nhiều đường trung tâm TP Biên Hòa và một số quận huyện TP HCM ngập 30-40 cm, người đi xe máy ngã nhào, nhà tốc mái, chiều 7/5.",
      "date_published": "2024-05-07T10:24:20.000Z"
    },
    {
      "guid": "https://vnexpress.net/chu-oto-mien-dang-kiem-lan-dau-phai-nop-phi-lap-ho-so-4743124.html",
      "url": "https://vnexpress.net/chu-oto-mien-dang-kiem-lan-dau-phai-nop-phi-lap-ho-so-4743124.html",
      "title": "Chủ ôtô miễn đăng kiểm lần đầu phải nộp phí lập hồ sơ",
      "content_html": "<a href=\"https://vnexpress.net/chu-oto-mien-dang-kiem-lan-dau-phai-nop-phi-lap-ho-so-4743124.html\"><img src=\"https://vcdn1-vnexpress.vnecdn.net/2024/05/07/l1003444-jpg-4174-1679444363-1-6700-1777-1715068799.jpg?w=1200&h=0&q=100&dpr=1&fit=crop&s=dg997I1d4d5HGvbUAr6TaQ\"></a></br>Chủ ôtô được miễn đăng kiểm lần đầu phải trả phí lập hồ sơ phương tiện gần 50.000 đồng, từ ngày 15/6.",
      "summary": "<a href=\"https://vnexpress.net/chu-oto-mien-dang-kiem-lan-dau-phai-nop-phi-lap-ho-so-4743124.html\"><img src=\"https://vcdn1-vnexpress.vnecdn.net/2024/05/07/l1003444-jpg-4174-1679444363-1-6700-1777-1715068799.jpg?w=1200&h=0&q=100&dpr=1&fit=crop&s=dg997I1d4d5HGvbUAr6TaQ\"></a></br>Chủ ôtô được miễn đăng kiểm lần đầu phải trả phí lập hồ sơ phương tiện gần 50.000 đồng, từ ngày 15/6.",
      "date_published": "2024-05-07T09:47:42.000Z"
    },
    {
      "guid": "https://vnexpress.net/tru-den-chieu-sang-do-trung-nguoi-di-xe-may-4743053.html",
      "url": "https://vnexpress.net/tru-den-chieu-sang-do-trung-nguoi-di-xe-may-4743053.html",
      "title": "Trụ đèn chiếu sáng đổ trúng người đi xe máy",
      "content_html": "<a href=\"https://vnexpress.net/tru-den-chieu-sang-do-trung-nguoi-di-xe-may-4743053.html\"><img src=\"https://vcdn1-vnexpress.vnecdn.net/2024/05/07/2c65d7b5bfce1e9047df-171506186-8250-8745-1715061957.jpg?w=1200&h=0&q=100&dpr=1&fit=crop&s=SLn-pa8SW0TNfjcGB8XsOQ\"></a></br>Trụ đèn chiếu sáng cao khoảng 5 m trên cầu vượt Tân Thới Hiệp, quận 12 bất ngờ đổ xuống đường khiến người đi đường bị thương, trưa 7/5.",
      "summary": "<a href=\"https://vnexpress.net/tru-den-chieu-sang-do-trung-nguoi-di-xe-may-4743053.html\"><img src=\"https://vcdn1-vnexpress.vnecdn.net/2024/05/07/2c65d7b5bfce1e9047df-171506186-8250-8745-1715061957.jpg?w=1200&h=0&q=100&dpr=1&fit=crop&s=SLn-pa8SW0TNfjcGB8XsOQ\"></a></br>Trụ đèn chiếu sáng cao khoảng 5 m trên cầu vượt Tân Thới Hiệp, quận 12 bất ngờ đổ xuống đường khiến người đi đường bị thương, trưa 7/5.",
      "date_published": "2024-05-07T06:30:16.000Z"
    },
    {
      "guid": "https://vnexpress.net/hien-truong-vu-lo-nui-vui-lap-7-cong-nhan-4743020.html",
      "url": "https://vnexpress.net/hien-truong-vu-lo-nui-vui-lap-7-cong-nhan-4743020.html",
      "title": "Hiện trường vụ lở núi vùi lấp 7 công nhân",
      "content_html": "<a href=\"https://vnexpress.net/hien-truong-vu-lo-nui-vui-lap-7-cong-nhan-4743020.html\"><img src=\"https://vcdn1-vnexpress.vnecdn.net/2024/05/07/17-JPG-1715056273.jpg?w=1200&h=0&q=100&dpr=1&fit=crop&s=BrNKn0UR57JZVwZ1o-ij_g\"></a></br>Lán trại, vật dụng sinh hoạt ngổn ngang, lấm lem bùn đất sau vụ lở núi ở thị xã Kỳ Anh làm 3 người chết, 4 người bị thương.",
      "summary": "<a href=\"https://vnexpress.net/hien-truong-vu-lo-nui-vui-lap-7-cong-nhan-4743020.html\"><img src=\"https://vcdn1-vnexpress.vnecdn.net/2024/05/07/17-JPG-1715056273.jpg?w=1200&h=0&q=100&dpr=1&fit=crop&s=BrNKn0UR57JZVwZ1o-ij_g\"></a></br>Lán trại, vật dụng sinh hoạt ngổn ngang, lấm lem bùn đất sau vụ lở núi ở thị xã Kỳ Anh làm 3 người chết, 4 người bị thương.",
      "date_published": "2024-05-07T06:18:42.000Z"
    },
    {
      "guid": "https://vnexpress.net/nhung-hinh-anh-an-tuong-trong-le-dieu-binh-tai-dien-bien-phu-4742980.html",
      "url": "https://vnexpress.net/nhung-hinh-anh-an-tuong-trong-le-dieu-binh-tai-dien-bien-phu-4742980.html",
      "title": "Những hình ảnh ấn tượng trong lễ diễu binh tại Điện Biên Phủ",
      "content_html": "<a href=\"https://vnexpress.net/nhung-hinh-anh-an-tuong-trong-le-dieu-binh-tai-dien-bien-phu-4742980.html\"><img src=\"https://vcdn1-vnexpress.vnecdn.net/2024/05/07/dieu-binh-mung-chien-thang-70-nam-Dien-Bien-Phu.jpg?w=1200&h=0&q=100&dpr=1&fit=crop&s=0uOzFKb_Q94ZOzBifHgyGA\"></a></br>Hình ảnh em bé Điện Biên dưới cờ Tổ quốc, hay biển người chào đón đoàn diễu binh gây xúc động cho nhiều  người trong lễ kỷ niệm 70 năm chiến thắng Điện Biên Phủ.",
      "summary": "<a href=\"https://vnexpress.net/nhung-hinh-anh-an-tuong-trong-le-dieu-binh-tai-dien-bien-phu-4742980.html\"><img src=\"https://vcdn1-vnexpress.vnecdn.net/2024/05/07/dieu-binh-mung-chien-thang-70-nam-Dien-Bien-Phu.jpg?w=1200&h=0&q=100&dpr=1&fit=crop&s=0uOzFKb_Q94ZOzBifHgyGA\"></a></br>Hình ảnh em bé Điện Biên dưới cờ Tổ quốc, hay biển người chào đón đoàn diễu binh gây xúc động cho nhiều  người trong lễ kỷ niệm 70 năm chiến thắng Điện Biên Phủ.",
      "date_published": "2024-05-07T04:48:25.000Z"
    },
    {
      "guid": "https://vnexpress.net/nguoi-dan-doi-mua-xem-dieu-binh-ky-niem-70-nam-chien-thang-dien-bien-4742913.html",
      "url": "https://vnexpress.net/nguoi-dan-doi-mua-xem-dieu-binh-ky-niem-70-nam-chien-thang-dien-bien-4742913.html",
      "title": "Người dân đội mưa xem diễu binh kỷ niệm 70 năm chiến thắng Điện Biên",
      "content_html": "<a href=\"https://vnexpress.net/nguoi-dan-doi-mua-xem-dieu-binh-ky-niem-70-nam-chien-thang-dien-bien-4742913.html\"><img src=\"https://vcdn1-vnexpress.vnecdn.net/2024/05/07/mua-17-jpg-1715050286-1715050339.jpg?w=1200&h=0&q=100&dpr=1&fit=crop&s=x0a-GIVPunSmitQAk1G4Gg\"></a></br>Hàng nghìn người dân, du khách đội mưa chờ xem diễu binh, diễu hành kỷ niệm 70 năm chiến thắng Điện Biên Phủ, sáng 7/5.",
      "summary": "<a href=\"https://vnexpress.net/nguoi-dan-doi-mua-xem-dieu-binh-ky-niem-70-nam-chien-thang-dien-bien-4742913.html\"><img src=\"https://vcdn1-vnexpress.vnecdn.net/2024/05/07/mua-17-jpg-1715050286-1715050339.jpg?w=1200&h=0&q=100&dpr=1&fit=crop&s=x0a-GIVPunSmitQAk1G4Gg\"></a></br>Hàng nghìn người dân, du khách đội mưa chờ xem diễu binh, diễu hành kỷ niệm 70 năm chiến thắng Điện Biên Phủ, sáng 7/5.",
      "date_published": "2024-05-07T02:39:02.000Z"
    },
    {
      "guid": "https://vnexpress.net/truc-tiep-dieu-binh-dieu-hanh-ky-niem-70-nam-chien-thang-dien-bien-phu-4742623-tong-thuat.html",
      "url": "https://vnexpress.net/truc-tiep-dieu-binh-dieu-hanh-ky-niem-70-nam-chien-thang-dien-bien-phu-4742623-tong-thuat.html",
      "title": "Lễ diễu binh diễu hành mừng chiến thắng Điện Biên Phủ",
      "content_html": "<a href=\"https://vnexpress.net/truc-tiep-dieu-binh-dieu-hanh-ky-niem-70-nam-chien-thang-dien-bien-phu-4742623-tong-thuat.html\"><img src=\"https://vcdn1-vnexpress.vnecdn.net/2024/05/07/anhsetkhac1-1715056647-7819-1715056652.jpg?w=1200&h=0&q=100&dpr=1&fit=crop&s=7auDUIB4e57rvQje5YqNsw\"></a></br>10h20 ngày 7/5, lễ kỷ niệm chiến thắng Điện Biên Phủ khép lại sau khoảng 2 tiếng diễu binh diễu hành của hơn 12.000 người từ 40 khối quân binh chủng và đoàn thể.",
      "summary": "<a href=\"https://vnexpress.net/truc-tiep-dieu-binh-dieu-hanh-ky-niem-70-nam-chien-thang-dien-bien-phu-4742623-tong-thuat.html\"><img src=\"https://vcdn1-vnexpress.vnecdn.net/2024/05/07/anhsetkhac1-1715056647-7819-1715056652.jpg?w=1200&h=0&q=100&dpr=1&fit=crop&s=7auDUIB4e57rvQje5YqNsw\"></a></br>10h20 ngày 7/5, lễ kỷ niệm chiến thắng Điện Biên Phủ khép lại sau khoảng 2 tiếng diễu binh diễu hành của hơn 12.000 người từ 40 khối quân binh chủng và đoàn thể.",
      "date_published": "2024-05-07T00:00:00.000Z"
    },
    {
      "guid": "https://vnexpress.net/cong-nhan-ke-giay-phut-thoat-khoi-ho-bun-sau-lo-nui-4742801.html",
      "url": "https://vnexpress.net/cong-nhan-ke-giay-phut-thoat-khoi-ho-bun-sau-lo-nui-4742801.html",
      "title": "Công nhân kể giây phút thoát khỏi hố bùn sau lở núi",
      "content_html": "<a href=\"https://vnexpress.net/cong-nhan-ke-giay-phut-thoat-khoi-ho-bun-sau-lo-nui-4742801.html\"><img src=\"https://vcdn1-vnexpress.vnecdn.net/2024/05/06/ongdonganhngoc-1715013841-5916-1715014380.jpg?w=1200&h=0&q=100&dpr=1&fit=crop&s=ZI2BiLjs-vQT4AMkxj97ZA\"></a></br>Thấy trời đổ mưa lớn, sấm chớp liên hồi, ông Đồng Ánh Ngọc giục 17 đồng nghiệp thu gom đồ đạc rời đi nhưng chỉ vài giây sau đất đá ập xuống vùi lấp lán trại cùng 7 người.",
      "summary": "<a href=\"https://vnexpress.net/cong-nhan-ke-giay-phut-thoat-khoi-ho-bun-sau-lo-nui-4742801.html\"><img src=\"https://vcdn1-vnexpress.vnecdn.net/2024/05/06/ongdonganhngoc-1715013841-5916-1715014380.jpg?w=1200&h=0&q=100&dpr=1&fit=crop&s=ZI2BiLjs-vQT4AMkxj97ZA\"></a></br>Thấy trời đổ mưa lớn, sấm chớp liên hồi, ông Đồng Ánh Ngọc giục 17 đồng nghiệp thu gom đồ đạc rời đi nhưng chỉ vài giây sau đất đá ập xuống vùi lấp lán trại cùng 7 người.",
      "date_published": "2024-05-06T18:10:40.000Z"
    },
    {
      "guid": "https://vnexpress.net/phao-hoa-ruc-sang-ben-cau-muong-thanh-4742800.html",
      "url": "https://vnexpress.net/phao-hoa-ruc-sang-ben-cau-muong-thanh-4742800.html",
      "title": "Pháo hoa rực sáng bên cầu Mường Thanh",
      "content_html": "<a href=\"https://vnexpress.net/phao-hoa-ruc-sang-ben-cau-muong-thanh-4742800.html\"><img src=\"https://vcdn1-vnexpress.vnecdn.net/2024/05/06/L1130042-1715013028.jpg?w=1200&h=0&q=100&dpr=1&fit=crop&s=zFxAl7lwZltki94jpc7l3A\"></a></br>Màn pháo hoa tầm cao kéo dài 15 phút dưới chân cầu Mường Thanh khiến TP Điện Biên Phủ rực rỡ trong đêm.",
      "summary": "<a href=\"https://vnexpress.net/phao-hoa-ruc-sang-ben-cau-muong-thanh-4742800.html\"><img src=\"https://vcdn1-vnexpress.vnecdn.net/2024/05/06/L1130042-1715013028.jpg?w=1200&h=0&q=100&dpr=1&fit=crop&s=zFxAl7lwZltki94jpc7l3A\"></a></br>Màn pháo hoa tầm cao kéo dài 15 phút dưới chân cầu Mường Thanh khiến TP Điện Biên Phủ rực rỡ trong đêm.",
      "date_published": "2024-05-06T17:24:07.000Z"
    },
    {
      "guid": "https://vnexpress.net/yeu-cau-day-nhanh-tien-do-cao-toc-bien-hoa-vung-tau-truoc-mua-mua-4742764.html",
      "url": "https://vnexpress.net/yeu-cau-day-nhanh-tien-do-cao-toc-bien-hoa-vung-tau-truoc-mua-mua-4742764.html",
      "title": "Yêu cầu đẩy nhanh tiến độ cao tốc Biên Hoà - Vũng Tàu trước mùa mưa",
      "content_html": "<a href=\"https://vnexpress.net/yeu-cau-day-nhanh-tien-do-cao-toc-bien-hoa-vung-tau-truoc-mua-mua-4742764.html\"><img src=\"https://vcdn1-vnexpress.vnecdn.net/2024/05/06/z541523543257665153447ec48c418-4601-9689-1715002833.jpg?w=1200&h=0&q=100&dpr=1&fit=crop&s=b_SafWvdTUctfdtrX1V58w\"></a></br>Lãnh đạo Bộ Giao thông Vận tải yêu cầu Đồng Nai sớm giao thêm mặt bằng để tận dụng thuận lợi những ngày cuối cùng của mùa khô, đẩy nhanh tiến độ thi công.",
      "summary": "<a href=\"https://vnexpress.net/yeu-cau-day-nhanh-tien-do-cao-toc-bien-hoa-vung-tau-truoc-mua-mua-4742764.html\"><img src=\"https://vcdn1-vnexpress.vnecdn.net/2024/05/06/z541523543257665153447ec48c418-4601-9689-1715002833.jpg?w=1200&h=0&q=100&dpr=1&fit=crop&s=b_SafWvdTUctfdtrX1V58w\"></a></br>Lãnh đạo Bộ Giao thông Vận tải yêu cầu Đồng Nai sớm giao thêm mặt bằng để tận dụng thuận lợi những ngày cuối cùng của mùa khô, đẩy nhanh tiến độ thi công.",
      "date_published": "2024-05-06T17:00:00.000Z"
    },
    {
      "guid": "https://vnexpress.net/pha-ngang-song-hau-ngung-chay-sau-hai-ngay-duoc-gia-han-4742760.html",
      "url": "https://vnexpress.net/pha-ngang-song-hau-ngung-chay-sau-hai-ngay-duoc-gia-han-4742760.html",
      "title": "Phà ngang sông Hậu ngưng chạy sau hai ngày được gia hạn",
      "content_html": "<a href=\"https://vnexpress.net/pha-ngang-song-hau-ngung-chay-sau-hai-ngay-duoc-gia-han-4742760.html\"><img src=\"https://vcdn1-vnexpress.vnecdn.net/2024/05/06/XUONG-GHE-NHO-VE-BINH-MINH-1858-1714999523.jpg?w=1200&h=0&q=100&dpr=1&fit=crop&s=Av1xiPdxJnoCBsbSY_hRvw\"></a></br>Sau 2 ngày được gia hạn, phà ngang sông Hậu nối Cần Thơ - Vĩnh Long lại bị ngưng hoạt động, người dân phải đi bằng xuồng máy, ghe nhỏ vượt sông mưu sinh, tiềm ẩn tai nạn.",
      "summary": "<a href=\"https://vnexpress.net/pha-ngang-song-hau-ngung-chay-sau-hai-ngay-duoc-gia-han-4742760.html\"><img src=\"https://vcdn1-vnexpress.vnecdn.net/2024/05/06/XUONG-GHE-NHO-VE-BINH-MINH-1858-1714999523.jpg?w=1200&h=0&q=100&dpr=1&fit=crop&s=Av1xiPdxJnoCBsbSY_hRvw\"></a></br>Sau 2 ngày được gia hạn, phà ngang sông Hậu nối Cần Thơ - Vĩnh Long lại bị ngưng hoạt động, người dân phải đi bằng xuồng máy, ghe nhỏ vượt sông mưu sinh, tiềm ẩn tai nạn.",
      "date_published": "2024-05-06T14:49:48.000Z"
    },
    {
      "guid": "https://vnexpress.net/bo-truong-quoc-phong-phap-tham-di-tich-dien-bien-phu-4742769.html",
      "url": "https://vnexpress.net/bo-truong-quoc-phong-phap-tham-di-tich-dien-bien-phu-4742769.html",
      "title": "Bộ trưởng Quốc phòng Pháp thăm di tích Điện Biên Phủ",
      "content_html": "<a href=\"https://vnexpress.net/bo-truong-quoc-phong-phap-tham-di-tich-dien-bien-phu-4742769.html\"><img src=\"https://vcdn1-vnexpress.vnecdn.net/2024/05/06/nmq-0874-1715001656-1715004209.jpg?w=1200&h=0&q=100&dpr=1&fit=crop&s=QWmgoSU0swK8akHhBqqjew\"></a></br>Bộ trưởng Quốc phòng Pháp Sébastien Lecornu thăm di tích đồi A1, hầm De Castries ở TP Điện Biên Phủ, chiều 6/5.",
      "summary": "<a href=\"https://vnexpress.net/bo-truong-quoc-phong-phap-tham-di-tich-dien-bien-phu-4742769.html\"><img src=\"https://vcdn1-vnexpress.vnecdn.net/2024/05/06/nmq-0874-1715001656-1715004209.jpg?w=1200&h=0&q=100&dpr=1&fit=crop&s=QWmgoSU0swK8akHhBqqjew\"></a></br>Bộ trưởng Quốc phòng Pháp Sébastien Lecornu thăm di tích đồi A1, hầm De Castries ở TP Điện Biên Phủ, chiều 6/5.",
      "date_published": "2024-05-06T14:26:50.000Z"
    },
    {
      "guid": "https://vnexpress.net/lo-nui-3-cong-nhan-tu-vong-4742739.html",
      "url": "https://vnexpress.net/lo-nui-3-cong-nhan-tu-vong-4742739.html",
      "title": "Lở núi, 3 công nhân tử vong",
      "content_html": "<a href=\"https://vnexpress.net/lo-nui-3-cong-nhan-tu-vong-4742739.html\"><img src=\"https://vcdn1-vnexpress.vnecdn.net/2024/05/06/cuu-ho-dua-ra-ngoai-6084-17149-3154-7116-1714998244.jpg?w=1200&h=0&q=100&dpr=1&fit=crop&s=0asFghNoTZsacGyzNR9HRQ\"></a></br>Nhóm công nhân trú mưa tại lán trại dưới chân núi ở thị xã Kỳ Anh thì bất ngờ núi lở, vùi chết 3 người, làm 4 người khác bị thương, chiều 6/5.",
      "summary": "<a href=\"https://vnexpress.net/lo-nui-3-cong-nhan-tu-vong-4742739.html\"><img src=\"https://vcdn1-vnexpress.vnecdn.net/2024/05/06/cuu-ho-dua-ra-ngoai-6084-17149-3154-7116-1714998244.jpg?w=1200&h=0&q=100&dpr=1&fit=crop&s=0asFghNoTZsacGyzNR9HRQ\"></a></br>Nhóm công nhân trú mưa tại lán trại dưới chân núi ở thị xã Kỳ Anh thì bất ngờ núi lở, vùi chết 3 người, làm 4 người khác bị thương, chiều 6/5.",
      "date_published": "2024-05-06T11:11:12.000Z"
    },
    {
      "guid": "https://vnexpress.net/giong-loc-danh-chim-tau-11-ngu-dan-mat-tich-4742701.html",
      "url": "https://vnexpress.net/giong-loc-danh-chim-tau-11-ngu-dan-mat-tich-4742701.html",
      "title": "Giông lốc đánh chìm tàu, 11 ngư dân mất tích",
      "content_html": "<a href=\"https://vnexpress.net/giong-loc-danh-chim-tau-11-ngu-dan-mat-tich-4742701.html\"><img src=\"https://vcdn1-vnexpress.vnecdn.net/2024/05/06/1-9082-1714975297-1714992910-2-5371-5009-1714993339.jpg?w=1200&h=0&q=100&dpr=1&fit=crop&s=S9HsBu-5Ivrq9YW4TuZmpg\"></a></br>Giông lốc 5 ngày qua đã đánh chìm 5 tàu thuyền của ngư dân Quảng Bình và Quảng Ninh, làm 11 người mất tích, một người chết.",
      "summary": "<a href=\"https://vnexpress.net/giong-loc-danh-chim-tau-11-ngu-dan-mat-tich-4742701.html\"><img src=\"https://vcdn1-vnexpress.vnecdn.net/2024/05/06/1-9082-1714975297-1714992910-2-5371-5009-1714993339.jpg?w=1200&h=0&q=100&dpr=1&fit=crop&s=S9HsBu-5Ivrq9YW4TuZmpg\"></a></br>Giông lốc 5 ngày qua đã đánh chìm 5 tàu thuyền của ngư dân Quảng Bình và Quảng Ninh, làm 11 người mất tích, một người chết.",
      "date_published": "2024-05-06T10:29:25.000Z"
    },
    {
      "guid": "https://vnexpress.net/de-xuat-mo-them-hai-tuyen-buyt-mui-tran-o-tp-hcm-4742724.html",
      "url": "https://vnexpress.net/de-xuat-mo-them-hai-tuyen-buyt-mui-tran-o-tp-hcm-4742724.html",
      "title": "Đề xuất mở thêm hai tuyến buýt mui trần ở TP HCM",
      "content_html": "<a href=\"https://vnexpress.net/de-xuat-mo-them-hai-tuyen-buyt-mui-tran-o-tp-hcm-4742724.html\"><img src=\"https://vcdn1-vnexpress.vnecdn.net/2024/05/06/111-1714995849-2967-1714995879.jpg?w=1200&h=0&q=100&dpr=1&fit=crop&s=Lrki6YlpRAiloknHNNqShg\"></a></br>Sở Giao thông Vận tải thành phố kiến nghị mở thêm hai tuyến buýt hai tầng, thoáng nóc, chở khách tham quan khu nội đô, ngoài hai tuyến đã thí điểm.",
      "summary": "<a href=\"https://vnexpress.net/de-xuat-mo-them-hai-tuyen-buyt-mui-tran-o-tp-hcm-4742724.html\"><img src=\"https://vcdn1-vnexpress.vnecdn.net/2024/05/06/111-1714995849-2967-1714995879.jpg?w=1200&h=0&q=100&dpr=1&fit=crop&s=Lrki6YlpRAiloknHNNqShg\"></a></br>Sở Giao thông Vận tải thành phố kiến nghị mở thêm hai tuyến buýt hai tầng, thoáng nóc, chở khách tham quan khu nội đô, ngoài hai tuyến đã thí điểm.",
      "date_published": "2024-05-06T10:18:46.000Z"
    },
    {
      "guid": "https://vnexpress.net/chu-tich-quang-ngai-dang-van-minh-bi-bai-nhiem-4742696.html",
      "url": "https://vnexpress.net/chu-tich-quang-ngai-dang-van-minh-bi-bai-nhiem-4742696.html",
      "title": "Chủ tịch Quảng Ngãi Đặng Văn Minh bị bãi nhiệm",
      "content_html": "<a href=\"https://vnexpress.net/chu-tich-quang-ngai-dang-van-minh-bi-bai-nhiem-4742696.html\"><img src=\"https://vcdn1-vnexpress.vnecdn.net/2024/05/06/AngVnMinh-1714987393-4052-1714987554.jpg?w=1200&h=0&q=100&dpr=1&fit=crop&s=6rOLi7DZUAig01hGDd8e_Q\"></a></br>Ông Đặng Văn Minh, Chủ tịch UBND Quảng Ngãi bị HĐND tỉnh bãi nhiệm chức vụ do sai phạm liên quan vụ án tại Tập đoàn Phúc Sơn.",
      "summary": "<a href=\"https://vnexpress.net/chu-tich-quang-ngai-dang-van-minh-bi-bai-nhiem-4742696.html\"><img src=\"https://vcdn1-vnexpress.vnecdn.net/2024/05/06/AngVnMinh-1714987393-4052-1714987554.jpg?w=1200&h=0&q=100&dpr=1&fit=crop&s=6rOLi7DZUAig01hGDd8e_Q\"></a></br>Ông Đặng Văn Minh, Chủ tịch UBND Quảng Ngãi bị HĐND tỉnh bãi nhiệm chức vụ do sai phạm liên quan vụ án tại Tập đoàn Phúc Sơn.",
      "date_published": "2024-05-06T09:48:57.000Z"
    },
    {
      "guid": "https://vnexpress.net/anh-nuoi-cua-doan-dieu-binh-o-dien-bien-phu-4742597.html",
      "url": "https://vnexpress.net/anh-nuoi-cua-doan-dieu-binh-o-dien-bien-phu-4742597.html",
      "title": "'Anh nuôi' của đoàn diễu binh ở Điện Biên Phủ",
      "content_html": "<a href=\"https://vnexpress.net/anh-nuoi-cua-doan-dieu-binh-o-dien-bien-phu-4742597.html\"><img src=\"https://vcdn1-vnexpress.vnecdn.net/2024/05/06/dsc-6936-1714984830-1714984865.jpg?w=1200&h=0&q=100&dpr=1&fit=crop&s=IRiYuhBJtqww5l1w9Ype2A\"></a></br>2h mỗi ngày, chiến sĩ hậu cần Quân đoàn 12 dậy sơ chế thực phẩm, chuẩn bị bữa sáng cho 524 quân nhân thuộc bốn khối tham gia diễu binh mừng chiến thắng Điện Biên Phủ.",
      "summary": "<a href=\"https://vnexpress.net/anh-nuoi-cua-doan-dieu-binh-o-dien-bien-phu-4742597.html\"><img src=\"https://vcdn1-vnexpress.vnecdn.net/2024/05/06/dsc-6936-1714984830-1714984865.jpg?w=1200&h=0&q=100&dpr=1&fit=crop&s=IRiYuhBJtqww5l1w9Ype2A\"></a></br>2h mỗi ngày, chiến sĩ hậu cần Quân đoàn 12 dậy sơ chế thực phẩm, chuẩn bị bữa sáng cho 524 quân nhân thuộc bốn khối tham gia diễu binh mừng chiến thắng Điện Biên Phủ.",
      "date_published": "2024-05-06T08:11:43.000Z"
    },
    {
      "guid": "https://vnexpress.net/bo-truong-quoc-phong-phap-danh-gia-cao-doc-lap-tu-chu-cua-viet-nam-4742582.html",
      "url": "https://vnexpress.net/bo-truong-quoc-phong-phap-danh-gia-cao-doc-lap-tu-chu-cua-viet-nam-4742582.html",
      "title": "Bộ trưởng Quốc phòng Pháp đánh giá cao độc lập, tự chủ của Việt Nam",
      "content_html": "<a href=\"https://vnexpress.net/bo-truong-quoc-phong-phap-danh-gia-cao-doc-lap-tu-chu-cua-viet-nam-4742582.html\"><img src=\"https://vcdn1-vnexpress.vnecdn.net/2024/05/06/thrutuong-1714976617-4855-1714-2746-1356-1714987436.jpg?w=1200&h=0&q=100&dpr=1&fit=crop&s=Je_zfzkdim0Hpy96VlCwLA\"></a></br>Bộ trưởng Sébastien Lecornu khẳng định Pháp coi trọng quan hệ giữa hai nước và đánh giá cao độc lập, tự chủ của Việt Nam.",
      "summary": "<a href=\"https://vnexpress.net/bo-truong-quoc-phong-phap-danh-gia-cao-doc-lap-tu-chu-cua-viet-nam-4742582.html\"><img src=\"https://vcdn1-vnexpress.vnecdn.net/2024/05/06/thrutuong-1714976617-4855-1714-2746-1356-1714987436.jpg?w=1200&h=0&q=100&dpr=1&fit=crop&s=Je_zfzkdim0Hpy96VlCwLA\"></a></br>Bộ trưởng Sébastien Lecornu khẳng định Pháp coi trọng quan hệ giữa hai nước và đánh giá cao độc lập, tự chủ của Việt Nam.",
      "date_published": "2024-05-06T08:05:02.000Z"
    },
    {
      "guid": "https://vnexpress.net/tim-thay-thi-the-be-trai-sau-3-ngay-mat-tich-4742575.html",
      "url": "https://vnexpress.net/tim-thay-thi-the-be-trai-sau-3-ngay-mat-tich-4742575.html",
      "title": "Tìm thấy thi thể bé trai sau 3 ngày mất tích",
      "content_html": "<a href=\"https://vnexpress.net/tim-thay-thi-the-be-trai-sau-3-ngay-mat-tich-4742575.html\"><img src=\"https://vcdn1-vnexpress.vnecdn.net/2024/05/06/z5413594664236-56da9d654e2e646-5840-6028-1714978207.jpg?w=1200&h=0&q=100&dpr=1&fit=crop&s=jLMqBlsyymbIhQJI-tzG9g\"></a></br>Sau 3 ngày tìm kiếm, cơ quan chức năng phát hiện bé trai 8 tuổi dưới giếng bỏ hoang nằm cách nhà khoảng 800 m.",
      "summary": "<a href=\"https://vnexpress.net/tim-thay-thi-the-be-trai-sau-3-ngay-mat-tich-4742575.html\"><img src=\"https://vcdn1-vnexpress.vnecdn.net/2024/05/06/z5413594664236-56da9d654e2e646-5840-6028-1714978207.jpg?w=1200&h=0&q=100&dpr=1&fit=crop&s=jLMqBlsyymbIhQJI-tzG9g\"></a></br>Sau 3 ngày tìm kiếm, cơ quan chức năng phát hiện bé trai 8 tuổi dưới giếng bỏ hoang nằm cách nhà khoảng 800 m.",
      "date_published": "2024-05-06T06:25:27.000Z"
    },
    {
      "guid": "https://vnexpress.net/ca-chet-tren-song-ma-keo-dai-50-km-4742484.html",
      "url": "https://vnexpress.net/ca-chet-tren-song-ma-keo-dai-50-km-4742484.html",
      "title": "Cá chết trên sông Mã kéo dài 50 km",
      "content_html": "<a href=\"https://vnexpress.net/ca-chet-tren-song-ma-keo-dai-50-km-4742484.html\"><img src=\"https://vcdn1-vnexpress.vnecdn.net/2024/05/06/Ca-chet-2-5881-1714965343.jpg?w=1200&h=0&q=100&dpr=1&fit=crop&s=n6cwkN0Da13cGHEcliR9QA\"></a></br>Gần 14 tấn cá lồng, cá tự nhiên chết bất thường trên 40-50 km sông Mã qua các huyện Bá Thước, Cẩm Thủy và đang có dấu hiệu lan rộng.",
      "summary": "<a href=\"https://vnexpress.net/ca-chet-tren-song-ma-keo-dai-50-km-4742484.html\"><img src=\"https://vcdn1-vnexpress.vnecdn.net/2024/05/06/Ca-chet-2-5881-1714965343.jpg?w=1200&h=0&q=100&dpr=1&fit=crop&s=n6cwkN0Da13cGHEcliR9QA\"></a></br>Gần 14 tấn cá lồng, cá tự nhiên chết bất thường trên 40-50 km sông Mã qua các huyện Bá Thước, Cẩm Thủy và đang có dấu hiệu lan rộng.",
      "date_published": "2024-05-06T04:47:00.000Z"
    },
    {
      "guid": "https://vnexpress.net/lanh-dao-dang-nha-nuoc-vao-lang-vieng-chu-tich-ho-chi-minh-4742500.html",
      "url": "https://vnexpress.net/lanh-dao-dang-nha-nuoc-vao-lang-vieng-chu-tich-ho-chi-minh-4742500.html",
      "title": "Lãnh đạo Đảng, Nhà nước vào Lăng viếng Chủ tịch Hồ Chí Minh",
      "content_html": "<a href=\"https://vnexpress.net/lanh-dao-dang-nha-nuoc-vao-lang-vieng-chu-tich-ho-chi-minh-4742500.html\"><img src=\"https://vcdn1-vnexpress.vnecdn.net/2024/05/06/lng-1714966489-6124-1714966651.jpg?w=1200&h=0&q=100&dpr=1&fit=crop&s=PfJjOnVuNn1BFz6ysiqb3g\"></a></br>Đoàn lãnh đạo Đảng, Nhà nước vào Lăng viếng Chủ tịch Hồ Chí Minh nhân kỷ niệm 70 năm chiến thắng Điện Biên Phủ 7/5/1954.",
      "summary": "<a href=\"https://vnexpress.net/lanh-dao-dang-nha-nuoc-vao-lang-vieng-chu-tich-ho-chi-minh-4742500.html\"><img src=\"https://vcdn1-vnexpress.vnecdn.net/2024/05/06/lng-1714966489-6124-1714966651.jpg?w=1200&h=0&q=100&dpr=1&fit=crop&s=PfJjOnVuNn1BFz6ysiqb3g\"></a></br>Đoàn lãnh đạo Đảng, Nhà nước vào Lăng viếng Chủ tịch Hồ Chí Minh nhân kỷ niệm 70 năm chiến thắng Điện Biên Phủ 7/5/1954.",
      "date_published": "2024-05-06T04:28:42.000Z"
    },
    {
      "guid": "https://vnexpress.net/dien-bien-phu-rop-co-hoa-truoc-ngay-dai-le-4742289.html",
      "url": "https://vnexpress.net/dien-bien-phu-rop-co-hoa-truoc-ngay-dai-le-4742289.html",
      "title": "Điện Biên Phủ rợp cờ hoa trước ngày đại lễ",
      "content_html": "<a href=\"https://vnexpress.net/dien-bien-phu-rop-co-hoa-truoc-ngay-dai-le-4742289.html\"><img src=\"https://vcdn1-vnexpress.vnecdn.net/2024/05/06/1u0a1529-jpg-1714957741-1714959429.jpg?w=1200&h=0&q=100&dpr=1&fit=crop&s=Z1rlbZuG6CqyI39ePRbQ-Q\"></a></br>Chuẩn bị cho lễ kỷ niệm 70 năm chiến thắng Điện Biên Phủ ngày 7/5, nhiều tuyến đường trung tâm của thành phố được trang hoàng cờ hoa rực rỡ.",
      "summary": "<a href=\"https://vnexpress.net/dien-bien-phu-rop-co-hoa-truoc-ngay-dai-le-4742289.html\"><img src=\"https://vcdn1-vnexpress.vnecdn.net/2024/05/06/1u0a1529-jpg-1714957741-1714959429.jpg?w=1200&h=0&q=100&dpr=1&fit=crop&s=Z1rlbZuG6CqyI39ePRbQ-Q\"></a></br>Chuẩn bị cho lễ kỷ niệm 70 năm chiến thắng Điện Biên Phủ ngày 7/5, nhiều tuyến đường trung tâm của thành phố được trang hoàng cờ hoa rực rỡ.",
      "date_published": "2024-05-06T02:48:59.000Z"
    },
    {
      "guid": "https://vnexpress.net/tai-xe-xe-dau-keo-vi-pham-nong-do-con-dam-vao-nha-dan-4742375.html",
      "url": "https://vnexpress.net/tai-xe-xe-dau-keo-vi-pham-nong-do-con-dam-vao-nha-dan-4742375.html",
      "title": "Tài xế xe đầu kéo vi phạm nồng độ cồn, đâm vào nhà dân",
      "content_html": "<a href=\"https://vnexpress.net/tai-xe-xe-dau-keo-vi-pham-nong-do-con-dam-vao-nha-dan-4742375.html\"><img src=\"https://vcdn1-vnexpress.vnecdn.net/2024/05/06/img-1867-1714956059-5060-1714956069.jpg?w=1200&h=0&q=100&dpr=1&fit=crop&s=RAxmQxrgNEGEmvfmu_-mWw\"></a></br>Lái xe đầu kéo có nồng độ cồn 0,5 mg/lít khí thở, đâm vào nhà dân bên đường khiến một người chết, một người nguy kịch, 5 người bị thương.",
      "summary": "<a href=\"https://vnexpress.net/tai-xe-xe-dau-keo-vi-pham-nong-do-con-dam-vao-nha-dan-4742375.html\"><img src=\"https://vcdn1-vnexpress.vnecdn.net/2024/05/06/img-1867-1714956059-5060-1714956069.jpg?w=1200&h=0&q=100&dpr=1&fit=crop&s=RAxmQxrgNEGEmvfmu_-mWw\"></a></br>Lái xe đầu kéo có nồng độ cồn 0,5 mg/lít khí thở, đâm vào nhà dân bên đường khiến một người chết, một người nguy kịch, 5 người bị thương.",
      "date_published": "2024-05-06T00:53:19.000Z"
    },
    {
      "guid": "https://vnexpress.net/cuoc-song-chien-si-dien-bien-70-nam-sau-giai-phong-4738707.html",
      "url": "https://vnexpress.net/cuoc-song-chien-si-dien-bien-70-nam-sau-giai-phong-4738707.html",
      "title": "Cuộc sống chiến sĩ Điện Biên 70 năm sau giải phóng",
      "content_html": "<a href=\"https://vnexpress.net/cuoc-song-chien-si-dien-bien-70-nam-sau-giai-phong-4738707.html\"><img src=\"https://vcdn1-vnexpress.vnecdn.net/2024/05/04/02-1714648134-1714813048.jpg?w=1200&h=0&q=100&dpr=1&fit=crop&s=YzNCAqrlGvSUSK6TSrJ_7g\"></a></br>Sau chiến thắng Điện Biên Phủ, ông Hoàng Văn Bảy về quê lấy vợ, đến năm 1958 trở lại làm nhiệm vụ khắc phục hậu quả chiến tranh, đưa gia đình lên lập nghiệp.",
      "summary": "<a href=\"https://vnexpress.net/cuoc-song-chien-si-dien-bien-70-nam-sau-giai-phong-4738707.html\"><img src=\"https://vcdn1-vnexpress.vnecdn.net/2024/05/04/02-1714648134-1714813048.jpg?w=1200&h=0&q=100&dpr=1&fit=crop&s=YzNCAqrlGvSUSK6TSrJ_7g\"></a></br>Sau chiến thắng Điện Biên Phủ, ông Hoàng Văn Bảy về quê lấy vợ, đến năm 1958 trở lại làm nhiệm vụ khắc phục hậu quả chiến tranh, đưa gia đình lên lập nghiệp.",
      "date_published": "2024-05-05T17:00:00.000Z"
    },
    {
      "guid": "https://vnexpress.net/cuu-binh-phap-tham-dien-bien-phu-4742296.html",
      "url": "https://vnexpress.net/cuu-binh-phap-tham-dien-bien-phu-4742296.html",
      "title": "Cựu binh Pháp thăm Điện Biên Phủ",
      "content_html": "<a href=\"https://vnexpress.net/cuu-binh-phap-tham-dien-bien-phu-4742296.html\"><img src=\"https://vcdn1-vnexpress.vnecdn.net/2024/05/05/DSC6495-1714911533-7998-1714911890.jpg?w=1200&h=0&q=100&dpr=1&fit=crop&s=9xUT7l-cxHBm96Y1_aj5BQ\"></a></br>Trở lại Điện Biên Phủ, các cựu binh tham quan bảo tàng, xem những hiện vật ở nơi binh lính Pháp từng tham chiến rồi bị đánh bại mùa hè 1954.",
      "summary": "<a href=\"https://vnexpress.net/cuu-binh-phap-tham-dien-bien-phu-4742296.html\"><img src=\"https://vcdn1-vnexpress.vnecdn.net/2024/05/05/DSC6495-1714911533-7998-1714911890.jpg?w=1200&h=0&q=100&dpr=1&fit=crop&s=9xUT7l-cxHBm96Y1_aj5BQ\"></a></br>Trở lại Điện Biên Phủ, các cựu binh tham quan bảo tàng, xem những hiện vật ở nơi binh lính Pháp từng tham chiến rồi bị đánh bại mùa hè 1954.",
      "date_published": "2024-05-05T15:19:28.000Z"
    },
    {
      "guid": "https://vnexpress.net/tai-nan-lien-hoan-cao-toc-ha-noi-lao-cai-te-liet-4742297.html",
      "url": "https://vnexpress.net/tai-nan-lien-hoan-cao-toc-ha-noi-lao-cai-te-liet-4742297.html",
      "title": "Tai nạn liên hoàn, cao tốc Hà Nội - Lào Cai tê liệt",
      "content_html": "<a href=\"https://vnexpress.net/tai-nan-lien-hoan-cao-toc-ha-noi-lao-cai-te-liet-4742297.html\"><img src=\"https://vcdn1-vnexpress.vnecdn.net/2024/05/05/z5411638967559-eb23ca348c3bb5d-3734-1522-1714917369.jpg?w=1200&h=0&q=100&dpr=1&fit=crop&s=6r8cTQAbQCZ_2RNN-h5pxA\"></a></br>Sau va chạm với xe con, ôtô tải chở hoa quả lật nghiêng, chắn hết chiều cao tốc hướng từ Lào Cai về Hà Nội, chiều 5/5.",
      "summary": "<a href=\"https://vnexpress.net/tai-nan-lien-hoan-cao-toc-ha-noi-lao-cai-te-liet-4742297.html\"><img src=\"https://vcdn1-vnexpress.vnecdn.net/2024/05/05/z5411638967559-eb23ca348c3bb5d-3734-1522-1714917369.jpg?w=1200&h=0&q=100&dpr=1&fit=crop&s=6r8cTQAbQCZ_2RNN-h5pxA\"></a></br>Sau va chạm với xe con, ôtô tải chở hoa quả lật nghiêng, chắn hết chiều cao tốc hướng từ Lào Cai về Hà Nội, chiều 5/5.",
      "date_published": "2024-05-05T12:58:06.000Z"
    },
    {
      "guid": "https://vnexpress.net/thong-xe-cau-vuot-thep-nut-mai-dich-4742019.html",
      "url": "https://vnexpress.net/thong-xe-cau-vuot-thep-nut-mai-dich-4742019.html",
      "title": "Thông xe cầu vượt thép nút Mai Dịch",
      "content_html": "<a href=\"https://vnexpress.net/thong-xe-cau-vuot-thep-nut-mai-dich-4742019.html\"><img src=\"https://vcdn1-vnexpress.vnecdn.net/2024/05/05/maidich2-1714900234-4038-1714900659.jpg?w=1200&h=0&q=100&dpr=1&fit=crop&s=WScQUArRb9VXLwKitHwdFA\"></a></br>Sáng 6/5, cầu thép tại nút giao Mai Dịch thông xe sau hơn một năm thi công nhằm giải quyết tình trạng tắc nghẽn ở nút giao trọng điểm này.",
      "summary": "<a href=\"https://vnexpress.net/thong-xe-cau-vuot-thep-nut-mai-dich-4742019.html\"><img src=\"https://vcdn1-vnexpress.vnecdn.net/2024/05/05/maidich2-1714900234-4038-1714900659.jpg?w=1200&h=0&q=100&dpr=1&fit=crop&s=WScQUArRb9VXLwKitHwdFA\"></a></br>Sáng 6/5, cầu thép tại nút giao Mai Dịch thông xe sau hơn một năm thi công nhằm giải quyết tình trạng tắc nghẽn ở nút giao trọng điểm này.",
      "date_published": "2024-05-05T11:19:17.000Z"
    },
    {
      "guid": "https://vnexpress.net/mua-va-giong-loc-o-long-an-tp-hcm-lam-toc-mai-cay-do-4742272.html",
      "url": "https://vnexpress.net/mua-va-giong-loc-o-long-an-tp-hcm-lam-toc-mai-cay-do-4742272.html",
      "title": "Mưa và giông lốc ở Long An, TP HCM làm tốc mái, cây đổ",
      "content_html": "<a href=\"https://vnexpress.net/mua-va-giong-loc-o-long-an-tp-hcm-lam-toc-mai-cay-do-4742272.html\"><img src=\"https://vcdn1-vnexpress.vnecdn.net/2024/05/05/2-1714904577-1714904660-5985-1714905005.jpg?w=1200&h=0&q=100&dpr=1&fit=crop&s=aE3N0JECU4tjPdaM0CuYCw\"></a></br>Cơn mưa lớn cùng giông lốc, nhiều phòng trọ ở Long An tốc mái, cột điện gãy, một số cây xanh tại TP HCM ngã đổ, chiều 5/5.",
      "summary": "<a href=\"https://vnexpress.net/mua-va-giong-loc-o-long-an-tp-hcm-lam-toc-mai-cay-do-4742272.html\"><img src=\"https://vcdn1-vnexpress.vnecdn.net/2024/05/05/2-1714904577-1714904660-5985-1714905005.jpg?w=1200&h=0&q=100&dpr=1&fit=crop&s=aE3N0JECU4tjPdaM0CuYCw\"></a></br>Cơn mưa lớn cùng giông lốc, nhiều phòng trọ ở Long An tốc mái, cột điện gãy, một số cây xanh tại TP HCM ngã đổ, chiều 5/5.",
      "date_published": "2024-05-05T10:32:45.000Z"
    },
    {
      "guid": "https://vnexpress.net/mien-bac-va-trung-tuan-toi-mat-me-4742259.html",
      "url": "https://vnexpress.net/mien-bac-va-trung-tuan-toi-mat-me-4742259.html",
      "title": "Miền Bắc và Trung tuần tới mát mẻ",
      "content_html": "<a href=\"https://vnexpress.net/mien-bac-va-trung-tuan-toi-mat-me-4742259.html\"><img src=\"https://vcdn1-vnexpress.vnecdn.net/2024/05/05/l1120779-jpg-1714904066-1218-1714904073.jpg?w=1200&h=0&q=100&dpr=1&fit=crop&s=hcfqFoMflmLy566PdIHhYQ\"></a></br>Không khí lạnh cuối mùa cùng hội tụ gió trên cao sẽ giúp miền Bắc duy trì tiết trời mát mẻ cả tuần sau, miền Trung chưa có dấu hiệu nắng nóng trở lại.",
      "summary": "<a href=\"https://vnexpress.net/mien-bac-va-trung-tuan-toi-mat-me-4742259.html\"><img src=\"https://vcdn1-vnexpress.vnecdn.net/2024/05/05/l1120779-jpg-1714904066-1218-1714904073.jpg?w=1200&h=0&q=100&dpr=1&fit=crop&s=hcfqFoMflmLy566PdIHhYQ\"></a></br>Không khí lạnh cuối mùa cùng hội tụ gió trên cao sẽ giúp miền Bắc duy trì tiết trời mát mẻ cả tuần sau, miền Trung chưa có dấu hiệu nắng nóng trở lại.",
      "date_published": "2024-05-05T09:58:15.000Z"
    },
    {
      "guid": "https://vnexpress.net/xuong-mut-xop-o-hung-yen-chay-lon-4742266.html",
      "url": "https://vnexpress.net/xuong-mut-xop-o-hung-yen-chay-lon-4742266.html",
      "title": "Xưởng mút xốp ở Hưng Yên cháy lớn",
      "content_html": "<a href=\"https://vnexpress.net/xuong-mut-xop-o-hung-yen-chay-lon-4742266.html\"><img src=\"https://vcdn1-vnexpress.vnecdn.net/2024/05/05/ClipchayHY-1714900335-8256-1714900364.gif?w=1200&h=0&q=100&dpr=1&fit=crop&s=K8Hwozzy6oLaqrutVh06Fw&t=image\"></a></br>Xưởng sản xuất mút xốp quây tôn ở xã Tân Việt, huyện Yên Mỹ cháy ngùn ngụt, cột khói đen bốc cao cả trăm mét, chiều 5/5.",
      "summary": "<a href=\"https://vnexpress.net/xuong-mut-xop-o-hung-yen-chay-lon-4742266.html\"><img src=\"https://vcdn1-vnexpress.vnecdn.net/2024/05/05/ClipchayHY-1714900335-8256-1714900364.gif?w=1200&h=0&q=100&dpr=1&fit=crop&s=K8Hwozzy6oLaqrutVh06Fw&t=image\"></a></br>Xưởng sản xuất mút xốp quây tôn ở xã Tân Việt, huyện Yên Mỹ cháy ngùn ngụt, cột khói đen bốc cao cả trăm mét, chiều 5/5.",
      "date_published": "2024-05-05T09:33:32.000Z"
    },
    {
      "guid": "https://vnexpress.net/viet-nam-phap-tang-cuong-hop-tac-quoc-phong-4742258.html",
      "url": "https://vnexpress.net/viet-nam-phap-tang-cuong-hop-tac-quoc-phong-4742258.html",
      "title": "Việt Nam - Pháp tăng cường hợp tác quốc phòng",
      "content_html": "<a href=\"https://vnexpress.net/viet-nam-phap-tang-cuong-hop-tac-quoc-phong-4742258.html\"><img src=\"https://vcdn1-vnexpress.vnecdn.net/2024/05/05/1137a339-3fdb-403d-a981-bd8cf1-6599-1574-1714899511.jpg?w=1200&h=0&q=100&dpr=1&fit=crop&s=xQTGOAJzLAMHkphQZVUOKA\"></a></br>Bộ trưởng Quốc phòng Việt Nam và Pháp đã ký ý định thư về tăng cường hợp tác quốc phòng tại buổi hội đàm, sáng 5/5.",
      "summary": "<a href=\"https://vnexpress.net/viet-nam-phap-tang-cuong-hop-tac-quoc-phong-4742258.html\"><img src=\"https://vcdn1-vnexpress.vnecdn.net/2024/05/05/1137a339-3fdb-403d-a981-bd8cf1-6599-1574-1714899511.jpg?w=1200&h=0&q=100&dpr=1&fit=crop&s=xQTGOAJzLAMHkphQZVUOKA\"></a></br>Bộ trưởng Quốc phòng Việt Nam và Pháp đã ký ý định thư về tăng cường hợp tác quốc phòng tại buổi hội đàm, sáng 5/5.",
      "date_published": "2024-05-05T08:51:46.000Z"
    },
    {
      "guid": "https://vnexpress.net/co-the-phat-hanh-trai-phieu-de-lam-vanh-dai-4-tp-hcm-4742242.html",
      "url": "https://vnexpress.net/co-the-phat-hanh-trai-phieu-de-lam-vanh-dai-4-tp-hcm-4742242.html",
      "title": "'Có thể phát hành trái phiếu để làm Vành đai 4 TP HCM'",
      "content_html": "<a href=\"https://vnexpress.net/co-the-phat-hanh-trai-phieu-de-lam-vanh-dai-4-tp-hcm-4742242.html\"><img src=\"https://vcdn1-vnexpress.vnecdn.net/2024/05/05/img4506-1714886109930561106938-9666-2244-1714895290.jpg?w=1200&h=0&q=100&dpr=1&fit=crop&s=uYfG8JWtpyz-eWXoJ2y8VQ\"></a></br>Vành đai 4 đầu tư lớn, song nguồn vốn hạn hẹp, các tỉnh thành có thể phát hành trái phiếu tìm kinh phí làm trước rồi trả sau, theo Bộ trưởng Kế hoạch và Đầu tư.",
      "summary": "<a href=\"https://vnexpress.net/co-the-phat-hanh-trai-phieu-de-lam-vanh-dai-4-tp-hcm-4742242.html\"><img src=\"https://vcdn1-vnexpress.vnecdn.net/2024/05/05/img4506-1714886109930561106938-9666-2244-1714895290.jpg?w=1200&h=0&q=100&dpr=1&fit=crop&s=uYfG8JWtpyz-eWXoJ2y8VQ\"></a></br>Vành đai 4 đầu tư lớn, song nguồn vốn hạn hẹp, các tỉnh thành có thể phát hành trái phiếu tìm kinh phí làm trước rồi trả sau, theo Bộ trưởng Kế hoạch và Đầu tư.",
      "date_published": "2024-05-05T07:51:49.000Z"
    },
    {
      "guid": "https://vnexpress.net/tong-duyet-dieu-binh-dieu-hanh-70-nam-chien-thang-dien-bien-phu-4742230.html",
      "url": "https://vnexpress.net/tong-duyet-dieu-binh-dieu-hanh-70-nam-chien-thang-dien-bien-phu-4742230.html",
      "title": "Tổng duyệt diễu binh, diễu hành 70 năm chiến thắng Điện Biên Phủ",
      "content_html": "<a href=\"https://vnexpress.net/tong-duyet-dieu-binh-dieu-hanh-70-nam-chien-thang-dien-bien-phu-4742230.html\"><img src=\"https://vcdn1-vnexpress.vnecdn.net/2024/05/05/dji-20240505084214-0048-d-jpg-1714886286-1714888591.jpg?w=1200&h=0&q=100&dpr=1&fit=crop&s=RABedKgP-khBfm4RrpL5xw\"></a></br>Hơn 12.000 người tham dự lễ tổng duyệt lễ diễu binh, diễu hành tại sân vận động tỉnh Điện Biên, sáng 5/5.",
      "summary": "<a href=\"https://vnexpress.net/tong-duyet-dieu-binh-dieu-hanh-70-nam-chien-thang-dien-bien-phu-4742230.html\"><img src=\"https://vcdn1-vnexpress.vnecdn.net/2024/05/05/dji-20240505084214-0048-d-jpg-1714886286-1714888591.jpg?w=1200&h=0&q=100&dpr=1&fit=crop&s=RABedKgP-khBfm4RrpL5xw\"></a></br>Hơn 12.000 người tham dự lễ tổng duyệt lễ diễu binh, diễu hành tại sân vận động tỉnh Điện Biên, sáng 5/5.",
      "date_published": "2024-05-05T06:03:21.000Z"
    },
    {
      "guid": "https://vnexpress.net/cam-xe-50-ngay-de-sua-cau-tren-quoc-lo-1-o-quang-ngai-4742172.html",
      "url": "https://vnexpress.net/cam-xe-50-ngay-de-sua-cau-tren-quoc-lo-1-o-quang-ngai-4742172.html",
      "title": "Cấm xe 50 ngày để sửa cầu trên quốc lộ 1 ở Quảng Ngãi",
      "content_html": "<a href=\"https://vnexpress.net/cam-xe-50-ngay-de-sua-cau-tren-quoc-lo-1-o-quang-ngai-4742172.html\"><img src=\"https://vcdn1-vnexpress.vnecdn.net/2024/05/05/tra-khuc-2-2-9304-1714875276-1-7619-2906-1714880444.jpg?w=1200&h=0&q=100&dpr=1&fit=crop&s=0w6xzKwx4vEdNi3mad4UFg\"></a></br>Cầu Trà Khúc 2 trên quốc lộ 1 xuất hiện nhiều vết nứt cần sửa chữa trong thời gian 50 ngày, các xe phải đi sang đường khác từ 10/5.",
      "summary": "<a href=\"https://vnexpress.net/cam-xe-50-ngay-de-sua-cau-tren-quoc-lo-1-o-quang-ngai-4742172.html\"><img src=\"https://vcdn1-vnexpress.vnecdn.net/2024/05/05/tra-khuc-2-2-9304-1714875276-1-7619-2906-1714880444.jpg?w=1200&h=0&q=100&dpr=1&fit=crop&s=0w6xzKwx4vEdNi3mad4UFg\"></a></br>Cầu Trà Khúc 2 trên quốc lộ 1 xuất hiện nhiều vết nứt cần sửa chữa trong thời gian 50 ngày, các xe phải đi sang đường khác từ 10/5.",
      "date_published": "2024-05-05T03:41:44.000Z"
    },
    {
      "guid": "https://vnexpress.net/truc-thang-bay-bieu-dien-tren-bau-troi-dien-bien-4742000.html",
      "url": "https://vnexpress.net/truc-thang-bay-bieu-dien-tren-bau-troi-dien-bien-4742000.html",
      "title": "Trực thăng bay biểu diễn trên bầu trời Điện Biên",
      "content_html": "<a href=\"https://vnexpress.net/truc-thang-bay-bieu-dien-tren-bau-troi-dien-bien-4742000.html\"><img src=\"https://vcdn1-vnexpress.vnecdn.net/2024/05/05/DSC-2877-1714883137.jpg?w=1200&h=0&q=100&dpr=1&fit=crop&s=Hy0IdsT0ZYTqJx0OFYbB_w\"></a></br>11 trực thăng bay biểu diễn kéo cờ Tổ quốc, cờ Đảng trong ngày tổng duyệt lễ kỷ niệm 70 năm chiến thắng Điện Biên Phủ, sáng 5/5.",
      "summary": "<a href=\"https://vnexpress.net/truc-thang-bay-bieu-dien-tren-bau-troi-dien-bien-4742000.html\"><img src=\"https://vcdn1-vnexpress.vnecdn.net/2024/05/05/DSC-2877-1714883137.jpg?w=1200&h=0&q=100&dpr=1&fit=crop&s=Hy0IdsT0ZYTqJx0OFYbB_w\"></a></br>11 trực thăng bay biểu diễn kéo cờ Tổ quốc, cờ Đảng trong ngày tổng duyệt lễ kỷ niệm 70 năm chiến thắng Điện Biên Phủ, sáng 5/5.",
      "date_published": "2024-05-05T02:27:24.000Z"
    },
    {
      "guid": "https://vnexpress.net/nguoi-giu-rung-u-minh-ha-4733499.html",
      "url": "https://vnexpress.net/nguoi-giu-rung-u-minh-ha-4733499.html",
      "title": "Những người 'canh lửa' ở rừng U Minh Hạ",
      "content_html": "<a href=\"https://vnexpress.net/nguoi-giu-rung-u-minh-ha-4733499.html\"><img src=\"https://vcdn1-vnexpress.vnecdn.net/2024/05/05/1-jpg-1712898773-6378-17129076-6506-4852-1714843771.jpg?w=1200&h=0&q=100&dpr=1&fit=crop&s=qFUYDJT7_Jymyc0ZNPpkIw\"></a></br>Trên chòi gác cao 20 m, rộng 3 m2, ngày nắng rát da, đêm đầy muỗi, nhân viên phải túc trực 24/24 canh giữ rừng, sớm phát hiện, ngăn nguy cơ cháy trong mùa khô hạn.",
      "summary": "<a href=\"https://vnexpress.net/nguoi-giu-rung-u-minh-ha-4733499.html\"><img src=\"https://vcdn1-vnexpress.vnecdn.net/2024/05/05/1-jpg-1712898773-6378-17129076-6506-4852-1714843771.jpg?w=1200&h=0&q=100&dpr=1&fit=crop&s=qFUYDJT7_Jymyc0ZNPpkIw\"></a></br>Trên chòi gác cao 20 m, rộng 3 m2, ngày nắng rát da, đêm đầy muỗi, nhân viên phải túc trực 24/24 canh giữ rừng, sớm phát hiện, ngăn nguy cơ cháy trong mùa khô hạn.",
      "date_published": "2024-05-05T00:46:01.000Z"
    },
    {
      "guid": "https://vnexpress.net/chien-dia-dien-bien-phu-sau-70-nam-4736615.html",
      "url": "https://vnexpress.net/chien-dia-dien-bien-phu-sau-70-nam-4736615.html",
      "title": "Chiến địa Điện Biên Phủ sau 70 năm",
      "content_html": "<a href=\"https://vnexpress.net/chien-dia-dien-bien-phu-sau-70-nam-4736615.html\"><img src=\"https://vcdn1-vnexpress.vnecdn.net/2024/04/27/17-jpg-1713606579-1714227504.jpg?w=1200&h=0&q=100&dpr=1&fit=crop&s=k0Ezb_zm6zxT6wM3AxHTsQ\"></a></br>Từng chằng chịt dây thép gai, bãi mìn, công sự, 70 năm sau thung lũng Điện Biên Phủ trở thành cánh đồng lúa, ngô xanh mướt, sân bay có thể tiếp nhận 300.000-500.000 khách mỗi năm.",
      "summary": "<a href=\"https://vnexpress.net/chien-dia-dien-bien-phu-sau-70-nam-4736615.html\"><img src=\"https://vcdn1-vnexpress.vnecdn.net/2024/04/27/17-jpg-1713606579-1714227504.jpg?w=1200&h=0&q=100&dpr=1&fit=crop&s=k0Ezb_zm6zxT6wM3AxHTsQ\"></a></br>Từng chằng chịt dây thép gai, bãi mìn, công sự, 70 năm sau thung lũng Điện Biên Phủ trở thành cánh đồng lúa, ngô xanh mướt, sân bay có thể tiếp nhận 300.000-500.000 khách mỗi năm.",
      "date_published": "2024-05-04T17:00:00.000Z"
    },
    {
      "guid": "https://vnexpress.net/ho-tro-hon-200-benh-nhi-co-them-co-hoi-song-4742115.html",
      "url": "https://vnexpress.net/ho-tro-hon-200-benh-nhi-co-them-co-hoi-song-4742115.html",
      "title": "Hỗ trợ hơn 200 bệnh nhi có thêm cơ hội sống",
      "content_html": "<a href=\"https://vnexpress.net/ho-tro-hon-200-benh-nhi-co-them-co-hoi-song-4742115.html\"><img src=\"https://vcdn1-vnexpress.vnecdn.net/2024/05/04/1-jpeg-1714833908-7121-1714834730.jpg?w=1200&h=0&q=100&dpr=1&fit=crop&s=3yEG-KnOO5QUd_MeEcj8EQ\"></a></br>Với mức hỗ trợ 20 đến 100 triệu đồng, Quỹ Hy vọng từ đầu năm đến nay đã giúp hơn 200 bệnh nhi ung thư có cơ hội tiếp cận các phương pháp điều trị tiên tiến, hiệu quả.",
      "summary": "<a href=\"https://vnexpress.net/ho-tro-hon-200-benh-nhi-co-them-co-hoi-song-4742115.html\"><img src=\"https://vcdn1-vnexpress.vnecdn.net/2024/05/04/1-jpeg-1714833908-7121-1714834730.jpg?w=1200&h=0&q=100&dpr=1&fit=crop&s=3yEG-KnOO5QUd_MeEcj8EQ\"></a></br>Với mức hỗ trợ 20 đến 100 triệu đồng, Quỹ Hy vọng từ đầu năm đến nay đã giúp hơn 200 bệnh nhi ung thư có cơ hội tiếp cận các phương pháp điều trị tiên tiến, hiệu quả.",
      "date_published": "2024-05-05T01:59:11.000Z"
    },
    {
      "guid": "https://vnexpress.net/lap-to-cong-tac-doc-thuc-tien-do-duong-sat-do-thi-ha-noi-tp-hcm-4742102.html",
      "url": "https://vnexpress.net/lap-to-cong-tac-doc-thuc-tien-do-duong-sat-do-thi-ha-noi-tp-hcm-4742102.html",
      "title": "Lập tổ công tác đốc thúc tiến độ đường sắt đô thị Hà Nội, TP HCM",
      "content_html": "<a href=\"https://vnexpress.net/lap-to-cong-tac-doc-thuc-tien-do-duong-sat-do-thi-ha-noi-tp-hcm-4742102.html\"><img src=\"https://vcdn1-vnexpress.vnecdn.net/2024/05/04/uongsat-1714830520-6967-1714830619.jpg?w=1200&h=0&q=100&dpr=1&fit=crop&s=VZZ8D8AXZGK9egou6SizjQ\"></a></br>Thủ tướng vừa ký quyết định lập tổ công tác giúp việc Ban Chỉ đạo, đốc thúc tiến độ triển khai các dự án đường sắt đô thị ở Hà Nội và TP HCM.",
      "summary": "<a href=\"https://vnexpress.net/lap-to-cong-tac-doc-thuc-tien-do-duong-sat-do-thi-ha-noi-tp-hcm-4742102.html\"><img src=\"https://vcdn1-vnexpress.vnecdn.net/2024/05/04/uongsat-1714830520-6967-1714830619.jpg?w=1200&h=0&q=100&dpr=1&fit=crop&s=VZZ8D8AXZGK9egou6SizjQ\"></a></br>Thủ tướng vừa ký quyết định lập tổ công tác giúp việc Ban Chỉ đạo, đốc thúc tiến độ triển khai các dự án đường sắt đô thị ở Hà Nội và TP HCM.",
      "date_published": "2024-05-04T15:30:51.000Z"
    },
    {
      "guid": "https://vnexpress.net/chien-si-dien-bien-vieng-dong-doi-o-nghia-trang-a1-4742082.html",
      "url": "https://vnexpress.net/chien-si-dien-bien-vieng-dong-doi-o-nghia-trang-a1-4742082.html",
      "title": "Chiến sĩ Điện Biên viếng đồng đội ở Nghĩa trang A1",
      "content_html": "<a href=\"https://vnexpress.net/chien-si-dien-bien-vieng-dong-doi-o-nghia-trang-a1-4742082.html\"><img src=\"https://vcdn1-vnexpress.vnecdn.net/2024/05/04/dsc-5014-1714822713-1714830469.jpg?w=1200&h=0&q=100&dpr=1&fit=crop&s=41MT2M1HXJ327YrSqi5AZw\"></a></br>Cựu binh ngồi trước những ngôi mộ ở Nghĩa trang liệt sĩ đồi A1, lầm rầm đọc tên từng đồng đội khắc trên bia đá, chiều 4/5.",
      "summary": "<a href=\"https://vnexpress.net/chien-si-dien-bien-vieng-dong-doi-o-nghia-trang-a1-4742082.html\"><img src=\"https://vcdn1-vnexpress.vnecdn.net/2024/05/04/dsc-5014-1714822713-1714830469.jpg?w=1200&h=0&q=100&dpr=1&fit=crop&s=41MT2M1HXJ327YrSqi5AZw\"></a></br>Cựu binh ngồi trước những ngôi mộ ở Nghĩa trang liệt sĩ đồi A1, lầm rầm đọc tên từng đồng đội khắc trên bia đá, chiều 4/5.",
      "date_published": "2024-05-04T14:26:49.000Z"
    },
    {
      "guid": "https://vnexpress.net/cam-nhieu-tuyen-duong-dip-ky-niem-70-nam-chien-thang-dien-bien-phu-4742084.html",
      "url": "https://vnexpress.net/cam-nhieu-tuyen-duong-dip-ky-niem-70-nam-chien-thang-dien-bien-phu-4742084.html",
      "title": "Cấm nhiều tuyến đường dịp kỷ niệm 70 năm chiến thắng Điện Biên Phủ",
      "content_html": "<a href=\"https://vnexpress.net/cam-nhieu-tuyen-duong-dip-ky-niem-70-nam-chien-thang-dien-bien-phu-4742084.html\"><img src=\"https://vcdn1-vnexpress.vnecdn.net/2024/05/04/b4c19a82-19a3-497a-afa0-fe2709-2285-3348-1714822693.jpg?w=1200&h=0&q=100&dpr=1&fit=crop&s=nE_gZ0M5whij8AZeMHUMQQ\"></a></br>UBND tỉnh thông báo cấm đường nhiều tuyến trong ba ngày 5-7/5 để chuẩn bị cho lễ kỷ niệm 70 năm chiến thắng Điện Biên Phủ.",
      "summary": "<a href=\"https://vnexpress.net/cam-nhieu-tuyen-duong-dip-ky-niem-70-nam-chien-thang-dien-bien-phu-4742084.html\"><img src=\"https://vcdn1-vnexpress.vnecdn.net/2024/05/04/b4c19a82-19a3-497a-afa0-fe2709-2285-3348-1714822693.jpg?w=1200&h=0&q=100&dpr=1&fit=crop&s=nE_gZ0M5whij8AZeMHUMQQ\"></a></br>UBND tỉnh thông báo cấm đường nhiều tuyến trong ba ngày 5-7/5 để chuẩn bị cho lễ kỷ niệm 70 năm chiến thắng Điện Biên Phủ.",
      "date_published": "2024-05-04T12:51:56.000Z"
    },
    {
      "guid": "https://vnexpress.net/luong-toi-thieu-cua-cong-chuc-khong-duoi-5-trieu-dong-4742047.html",
      "url": "https://vnexpress.net/luong-toi-thieu-cua-cong-chuc-khong-duoi-5-trieu-dong-4742047.html",
      "title": "Lương tối thiểu của công chức 'không dưới 5 triệu đồng'",
      "content_html": "<a href=\"https://vnexpress.net/luong-toi-thieu-cua-cong-chuc-khong-duoi-5-trieu-dong-4742047.html\"><img src=\"https://vcdn1-vnexpress.vnecdn.net/2024/05/04/bonoivu-1714820223-7190-1714820306.jpg?w=1200&h=0&q=100&dpr=1&fit=crop&s=82xwbhBQdZoyd6wcL-ir-Q\"></a></br>Bộ Nội vụ cho biết khi cải cách tiền lương sẽ đảm bảo công chức có mức lương thấp nhất không dưới 5 triệu đồng để họ \"có thể sống được bằng lương\".",
      "summary": "<a href=\"https://vnexpress.net/luong-toi-thieu-cua-cong-chuc-khong-duoi-5-trieu-dong-4742047.html\"><img src=\"https://vcdn1-vnexpress.vnecdn.net/2024/05/04/bonoivu-1714820223-7190-1714820306.jpg?w=1200&h=0&q=100&dpr=1&fit=crop&s=82xwbhBQdZoyd6wcL-ir-Q\"></a></br>Bộ Nội vụ cho biết khi cải cách tiền lương sẽ đảm bảo công chức có mức lương thấp nhất không dưới 5 triệu đồng để họ \"có thể sống được bằng lương\".",
      "date_published": "2024-05-04T12:32:39.000Z"
    },
    {
      "guid": "https://vnexpress.net/ha-noi-huy-ket-qua-3-mo-cat-dau-gia-xuyen-dem-4742071.html",
      "url": "https://vnexpress.net/ha-noi-huy-ket-qua-3-mo-cat-dau-gia-xuyen-dem-4742071.html",
      "title": "Hà Nội hủy kết quả 3 mỏ cát đấu giá xuyên đêm",
      "content_html": "<a href=\"https://vnexpress.net/ha-noi-huy-ket-qua-3-mo-cat-dau-gia-xuyen-dem-4742071.html\"><img src=\"https://vcdn1-vnexpress.vnecdn.net/2024/05/04/augia1-1714822112-4971-1714822364.jpg?w=1200&h=0&q=100&dpr=1&fit=crop&s=DvH_r7jsOh06X6ofT0I2AA\"></a></br>Hà Nội hủy kết quả đấu giá 3 mỏ cát Châu Sơn, Liên Mạc, Tây Đằng - Minh Châu vì giá trúng cao hơn giá thị trường và đơn vị trúng không đáp ứng vốn chủ sở hữu.",
      "summary": "<a href=\"https://vnexpress.net/ha-noi-huy-ket-qua-3-mo-cat-dau-gia-xuyen-dem-4742071.html\"><img src=\"https://vcdn1-vnexpress.vnecdn.net/2024/05/04/augia1-1714822112-4971-1714822364.jpg?w=1200&h=0&q=100&dpr=1&fit=crop&s=DvH_r7jsOh06X6ofT0I2AA\"></a></br>Hà Nội hủy kết quả đấu giá 3 mỏ cát Châu Sơn, Liên Mạc, Tây Đằng - Minh Châu vì giá trúng cao hơn giá thị trường và đơn vị trúng không đáp ứng vốn chủ sở hữu.",
      "date_published": "2024-05-04T12:12:42.000Z"
    },
    {
      "guid": "https://vnexpress.net/ba-truong-thi-mai-se-them-nguon-luc-ho-tro-dong-bao-dan-toc-thieu-so-4742074.html",
      "url": "https://vnexpress.net/ba-truong-thi-mai-se-them-nguon-luc-ho-tro-dong-bao-dan-toc-thieu-so-4742074.html",
      "title": "Bà Trương Thị Mai: Sẽ thêm nguồn lực hỗ trợ đồng bào dân tộc thiểu số",
      "content_html": "<a href=\"https://vnexpress.net/ba-truong-thi-mai-se-them-nguon-luc-ho-tro-dong-bao-dan-toc-thieu-so-4742074.html\"><img src=\"https://vcdn1-vnexpress.vnecdn.net/2024/05/04/440551959-672883068296904-1094-4030-6613-1714823027.jpg?w=1200&h=0&q=100&dpr=1&fit=crop&s=zqRYyNrvm37qE5F1tNoTnQ\"></a></br>Theo Thường trực Ban Bí thư, đồng bào dân tộc thiểu số sẽ tiếp tục được thụ hưởng chính sách, hỗ trợ nguồn lực để phát triển kinh tế từ nguồn ngân sách Trung ương.",
      "summary": "<a href=\"https://vnexpress.net/ba-truong-thi-mai-se-them-nguon-luc-ho-tro-dong-bao-dan-toc-thieu-so-4742074.html\"><img src=\"https://vcdn1-vnexpress.vnecdn.net/2024/05/04/440551959-672883068296904-1094-4030-6613-1714823027.jpg?w=1200&h=0&q=100&dpr=1&fit=crop&s=zqRYyNrvm37qE5F1tNoTnQ\"></a></br>Theo Thường trực Ban Bí thư, đồng bào dân tộc thiểu số sẽ tiếp tục được thụ hưởng chính sách, hỗ trợ nguồn lực để phát triển kinh tế từ nguồn ngân sách Trung ương.",
      "date_published": "2024-05-04T11:40:27.000Z"
    },
    {
      "guid": "https://vnexpress.net/dong-nam-bo-se-co-850-km-cao-toc-vao-nam-2030-4742067.html",
      "url": "https://vnexpress.net/dong-nam-bo-se-co-850-km-cao-toc-vao-nam-2030-4742067.html",
      "title": "Đông Nam Bộ sẽ có 850 km cao tốc vào năm 2030",
      "content_html": "<a href=\"https://vnexpress.net/dong-nam-bo-se-co-850-km-cao-toc-vao-nam-2030-4742067.html\"><img src=\"https://vcdn1-vnexpress.vnecdn.net/2024/05/04/89402A6A30279141228B5FEDC38E2F-6711-2169-1714820597.jpg?w=1200&h=0&q=100&dpr=1&fit=crop&s=6uzhV2tmqPqVADSUEGx48g\"></a></br>Đến năm 2030, Đông Nam Bộ sẽ hoàn thành cơ bản hệ thống kết cấu hạ tầng khung kết nối vùng và liên vùng, trong đó có khoảng 850 km đường bộ cao tốc.",
      "summary": "<a href=\"https://vnexpress.net/dong-nam-bo-se-co-850-km-cao-toc-vao-nam-2030-4742067.html\"><img src=\"https://vcdn1-vnexpress.vnecdn.net/2024/05/04/89402A6A30279141228B5FEDC38E2F-6711-2169-1714820597.jpg?w=1200&h=0&q=100&dpr=1&fit=crop&s=6uzhV2tmqPqVADSUEGx48g\"></a></br>Đến năm 2030, Đông Nam Bộ sẽ hoàn thành cơ bản hệ thống kết cấu hạ tầng khung kết nối vùng và liên vùng, trong đó có khoảng 850 km đường bộ cao tốc.",
      "date_published": "2024-05-04T11:03:55.000Z"
    },
    {
      "guid": "https://vnexpress.net/lo-hoi-no-khien-6-nguoi-chet-chua-co-giay-phep-hoat-dong-4742038.html",
      "url": "https://vnexpress.net/lo-hoi-no-khien-6-nguoi-chet-chua-co-giay-phep-hoat-dong-4742038.html",
      "title": "Lò hơi nổ khiến 6 người chết chưa có giấy phép hoạt động",
      "content_html": "<a href=\"https://vnexpress.net/lo-hoi-no-khien-6-nguoi-chet-chua-co-giay-phep-hoat-dong-4742038.html\"><img src=\"https://vcdn1-vnexpress.vnecdn.net/2024/05/04/z5408459049378578c637c7fb655bf-1992-2251-1714814619.jpg?w=1200&h=0&q=100&dpr=1&fit=crop&s=2qJ5jA7YPBbzHuOlVjUFsw\"></a></br>Qua kiểm tra hồ sơ, cơ quan chức năng tỉnh Đồng Nai phát hiện lò hơi nổ khiến 6 người chết chưa có giấy kiểm định, chưa được đăng ký sử dụng.",
      "summary": "<a href=\"https://vnexpress.net/lo-hoi-no-khien-6-nguoi-chet-chua-co-giay-phep-hoat-dong-4742038.html\"><img src=\"https://vcdn1-vnexpress.vnecdn.net/2024/05/04/z5408459049378578c637c7fb655bf-1992-2251-1714814619.jpg?w=1200&h=0&q=100&dpr=1&fit=crop&s=2qJ5jA7YPBbzHuOlVjUFsw\"></a></br>Qua kiểm tra hồ sơ, cơ quan chức năng tỉnh Đồng Nai phát hiện lò hơi nổ khiến 6 người chết chưa có giấy kiểm định, chưa được đăng ký sử dụng.",
      "date_published": "2024-05-04T09:57:36.000Z"
    },
    {
      "guid": "https://vnexpress.net/de-xuat-pho-chu-tich-huyen-duoc-thue-chung-cu-cong-vu-80-m2-4741772.html",
      "url": "https://vnexpress.net/de-xuat-pho-chu-tich-huyen-duoc-thue-chung-cu-cong-vu-80-m2-4741772.html",
      "title": "Đề xuất Phó chủ tịch huyện được thuê chung cư công vụ 80 m2",
      "content_html": "<a href=\"https://vnexpress.net/de-xuat-pho-chu-tich-huyen-duoc-thue-chung-cu-cong-vu-80-m2-4741772.html\"><img src=\"https://vcdn1-vnexpress.vnecdn.net/2024/05/04/nhacongvu-1714790566-9320-1714790990.jpg?w=1200&h=0&q=100&dpr=1&fit=crop&s=ofGYivqFwDsrUt8GtuXAEw\"></a></br>Phó chủ tịch UBND cấp huyện, Phó giám đốc Sở và tương đương trở lên có thể được thuê nhà công vụ là căn hộ chung cư 60-80 m2, thiết bị nội thất 120 triệu đồng.",
      "summary": "<a href=\"https://vnexpress.net/de-xuat-pho-chu-tich-huyen-duoc-thue-chung-cu-cong-vu-80-m2-4741772.html\"><img src=\"https://vcdn1-vnexpress.vnecdn.net/2024/05/04/nhacongvu-1714790566-9320-1714790990.jpg?w=1200&h=0&q=100&dpr=1&fit=crop&s=ofGYivqFwDsrUt8GtuXAEw\"></a></br>Phó chủ tịch UBND cấp huyện, Phó giám đốc Sở và tương đương trở lên có thể được thuê nhà công vụ là căn hộ chung cư 60-80 m2, thiết bị nội thất 120 triệu đồng.",
      "date_published": "2024-05-04T09:38:31.000Z"
    },
    {
      "guid": "https://vnexpress.net/sat-lo-bo-bao-bun-thai-o-bai-rac-lon-nhat-ha-noi-4741992.html",
      "url": "https://vnexpress.net/sat-lo-bo-bao-bun-thai-o-bai-rac-lon-nhat-ha-noi-4741992.html",
      "title": "Sạt lở bờ bao bùn thải ở bãi rác lớn nhất Hà Nội",
      "content_html": "<a href=\"https://vnexpress.net/sat-lo-bo-bao-bun-thai-o-bai-rac-lon-nhat-ha-noi-4741992.html\"><img src=\"https://vcdn1-vnexpress.vnecdn.net/2024/05/04/anh1-1714805098-6017-1714805443.jpg?w=1200&h=0&q=100&dpr=1&fit=crop&s=qrUKZ6wv7f5isr5w5_6Ttw\"></a></br>Bờ bao bãi Ô 1 bị sạt lở khiến bùn thải tràn xuống đường nội bộ tiếp giáp suối Lai Sơn trong khuôn viên bãi rác Nam Sơn, huyện Sóc Sơn.",
      "summary": "<a href=\"https://vnexpress.net/sat-lo-bo-bao-bun-thai-o-bai-rac-lon-nhat-ha-noi-4741992.html\"><img src=\"https://vcdn1-vnexpress.vnecdn.net/2024/05/04/anh1-1714805098-6017-1714805443.jpg?w=1200&h=0&q=100&dpr=1&fit=crop&s=qrUKZ6wv7f5isr5w5_6Ttw\"></a></br>Bờ bao bãi Ô 1 bị sạt lở khiến bùn thải tràn xuống đường nội bộ tiếp giáp suối Lai Sơn trong khuôn viên bãi rác Nam Sơn, huyện Sóc Sơn.",
      "date_published": "2024-05-04T07:40:25.000Z"
    },
    {
      "guid": "https://vnexpress.net/thi-diem-nguoi-dung-dau-gioi-thieu-nhan-su-bo-nhiem-cap-pho-4741976.html",
      "url": "https://vnexpress.net/thi-diem-nguoi-dung-dau-gioi-thieu-nhan-su-bo-nhiem-cap-pho-4741976.html",
      "title": "Thí điểm người đứng đầu giới thiệu nhân sự bổ nhiệm cấp phó",
      "content_html": "<a href=\"https://vnexpress.net/thi-diem-nguoi-dung-dau-gioi-thieu-nhan-su-bo-nhiem-cap-pho-4741976.html\"><img src=\"https://vcdn1-vnexpress.vnecdn.net/2024/05/04/202305052108039910-dsc-8362-17-8841-3076-1714803804.jpg?w=1200&h=0&q=100&dpr=1&fit=crop&s=zu_NXpwinQbV-mXgEekMYg\"></a></br>Bộ Chính trị thí điểm quy định cho phép người đứng đầu giới thiệu nhân sự bầu cử, bổ nhiệm làm cấp phó.",
      "summary": "<a href=\"https://vnexpress.net/thi-diem-nguoi-dung-dau-gioi-thieu-nhan-su-bo-nhiem-cap-pho-4741976.html\"><img src=\"https://vcdn1-vnexpress.vnecdn.net/2024/05/04/202305052108039910-dsc-8362-17-8841-3076-1714803804.jpg?w=1200&h=0&q=100&dpr=1&fit=crop&s=zu_NXpwinQbV-mXgEekMYg\"></a></br>Bộ Chính trị thí điểm quy định cho phép người đứng đầu giới thiệu nhân sự bầu cử, bổ nhiệm làm cấp phó.",
      "date_published": "2024-05-04T06:24:56.000Z"
    }
  ]
}